{"v":"4.8.0","meta":{"g":"LottieFiles AE 3.4.4","a":"","k":"","d":"","tc":""},"fr":29.9700012207031,"ip":0,"op":149.000006068894,"w":567,"h":689,"nm":"Since1976","ddd":0,"assets":[{"id":"comp_0","layers":[{"ddd":0,"ind":1,"ty":4,"nm":"색 O 일러/Since1976 Outlines","sr":1,"ks":{"o":{"a":0,"k":100,"ix":11},"r":{"a":0,"k":0,"ix":10},"p":{"a":0,"k":[68.5,77.5,0],"ix":2},"a":{"a":0,"k":[68.5,77.5,0],"ix":1},"s":{"a":0,"k":[100,100,100],"ix":6}},"ao":0,"shapes":[{"ty":"gr","it":[{"ind":0,"ty":"sh","ix":1,"ks":{"a":0,"k":{"i":[[1.4,-4.9],[0.8,-2.1],[2.9,-2.8],[2.3,-1.7],[0.2,-0.3],[5.9,-1.8],[3.9,-0.5],[0.4,-0.2],[2.1,-1.3],[2.1,-0.5],[4.5,2.9],[1.1,0.5],[1.6,4],[1.1,1],[0,-0.8],[1.8,1.3],[6.9,4.2],[2.1,0.1],[1.5,1.1],[1.2,1.9],[-0.7,2.9],[-1.6,4.2],[-0.1,0.7],[-0.3,-0.5],[-1.7,-2.1],[-8.4,-3],[-2.9,0.4],[0,-1],[-3.6,-3.5],[-5.2,-0.6],[-2.4,0.2],[-1.3,1.6],[-1,-0.1],[-1,-0.2],[0.4,1.1],[0.2,0.7],[0.5,-0.1],[1.2,1.5],[1.4,1.9],[3.4,1.7],[0.4,0.2],[-2.4,1.8],[-1.9,1.6],[-1.6,2.6],[-1.3,2],[-2,5.9],[0,0.1],[-2.8,-0.5],[-4.2,-1.6],[-0.7,-0.8],[-1,-6.7],[-1.6,-3],[-1.3,-3.7]],"o":[[-0.6,2.2],[-1.4,3.6],[-2,2],[-0.2,0.2],[-3.1,6.1],[-4,-0.2],[-0.4,0.1],[-2.2,0.5],[-1.9,1.1],[-5.2,1.3],[-1,-0.7],[-4,-1.9],[-0.6,-1.5],[-2.1,-0.6],[-1.6,-1.6],[-6.1,-1.5],[-1.8,-1.1],[-1.9,-0.2],[-1.8,-1.4],[-1.5,-2.2],[1,-4.3],[0.3,-0.7],[0.1,-0.6],[1.7,2.1],[5.5,7.3],[2.7,1],[0.8,-0.1],[0.2,5.3],[3.8,3.7],[2.4,0.3],[1.8,-0.2],[0.7,-0.9],[1,0.1],[1.2,0.3],[-0.3,-0.7],[-0.1,-0.5],[-2.3,0.2],[-1.6,-1.8],[-2.2,-3.1],[-0.4,-0.2],[-2.7,-1.5],[2,-1.6],[2.3,-2],[1.3,-2],[3.4,-5.1],[0.1,-0.1],[0.7,-2.5],[4.5,-0.4],[0.9,0.4],[4.5,4.7],[0.5,3.4],[1.9,3.4],[1.9,4.3]],"v":[[64.45,37.2],[62.75,43.7],[56.65,53.5],[50.75,59.6],[50.15,60.3],[35.35,70],[23.65,71.7],[22.35,71.9],[15.85,71.8],[9.75,73.4],[-4.75,71.1],[-7.95,69.4],[-16.45,65.3],[-19.25,61.4],[-21.35,61.5],[-30.15,59.8],[-44.85,55.1],[-50.95,36.2],[-53.75,30.6],[-58.35,25.7],[-59.95,18.1],[-56.65,5.2],[-56.25,3],[-54.95,2.6],[-49.75,8.8],[-28.45,23.7],[-20.05,24.4],[-18.55,25.6],[-12.05,38.4],[1.45,44.7],[8.65,44.9],[13.55,43.1],[16.45,42.4],[19.45,43.2],[20.85,41.8],[20.05,39.7],[19.25,38.9],[14.55,36],[9.95,30.5],[1.55,23.3],[0.35,22.7],[0.05,19.3],[5.85,14.4],[11.65,7.6],[15.65,1.7],[24.45,-14.3],[24.55,-14.7],[29.65,-17.9],[42.55,-15],[45.15,-13.2],[54.55,3.2],[58.35,12.7],[63.35,23.2]],"c":true},"ix":2},"nm":"Path 1","mn":"ADBE Vector Shape - Group","hd":false},{"ind":1,"ty":"sh","ix":2,"ks":{"a":0,"k":{"i":[[1.8,5.1],[0.1,3],[0.1,3.5],[-2.5,-2.6],[-1.4,-4],[-0.8,-3.2],[-2.7,-4.4],[-0.9,-1.4],[3.3,5.2],[1.1,1.2]],"o":[[-1,-2.8],[-0.1,-2.5],[3.4,3.3],[3,3.1],[1.1,3.1],[1.3,4.9],[0.8,1.3],[-4.9,-3.1],[-0.9,-1.4],[-3.8,-4.1]],"v":[[-58.65,-11.3],[-61.15,-19.8],[-61.35,-28.3],[-52.55,-20.3],[-46.05,-9.7],[-43.15,-0.3],[-36.65,13.4],[-33.75,17.2],[-47.35,6.3],[-50.45,2.5]],"c":true},"ix":2},"nm":"Path 2","mn":"ADBE Vector Shape - Group","hd":false},{"ind":2,"ty":"sh","ix":3,"ks":{"a":0,"k":{"i":[[-0.1,0.2],[-0.4,-0.2],[-0.7,-2.5],[1.6,1.7]],"o":[[0.3,-0.5],[2.1,1.2],[-2.2,-1.1],[-0.1,-0.2]],"v":[[-60.75,-33.3],[-59.55,-33.4],[-55.25,-27.9],[-60.65,-32.5]],"c":true},"ix":2},"nm":"Path 3","mn":"ADBE Vector Shape - Group","hd":false},{"ind":3,"ty":"sh","ix":4,"ks":{"a":0,"k":{"i":[[-0.4,0.1],[-2.6,-1.6],[-2.3,-3.6],[-2.5,-5.5],[-0.6,-3.8],[0,-0.4],[3.1,0.7],[1.8,2.9],[1,5.1],[2.9,4.9],[2.1,2.6]],"o":[[3.2,-1.3],[3.6,2.2],[3.3,5.2],[1.6,3.6],[0.1,0.4],[-0.2,3],[-3.4,-0.7],[-2.7,-4.3],[-1.1,-5.6],[-1.4,-2.4],[0.8,0]],"v":[[-50.85,-25.5],[-42.55,-23.8],[-33.85,-14.9],[-25.35,1.2],[-22.65,12.4],[-22.65,13.7],[-26.65,16.4],[-34.45,10.9],[-40.65,-2.8],[-46.95,-18.4],[-52.55,-25.4]],"c":true},"ix":2},"nm":"Path 4","mn":"ADBE Vector Shape - Group","hd":false},{"ind":4,"ty":"sh","ix":5,"ks":{"a":0,"k":{"i":[[0,7.9],[-1.7,6.3],[-1.6,0.3],[-0.9,-5.8],[0.7,-2.3],[-0.6,-6.2],[0.2,-0.3]],"o":[[0,-6.7],[0.2,-0.9],[1.7,5.7],[0.4,2.4],[-1.8,5.9],[0,0.2],[-5.3,-6.2]],"v":[[-32.55,-31.7],[-28.95,-50.9],[-27.05,-53.4],[-22.75,-36.3],[-23.55,-29.2],[-25.55,-11.1],[-25.95,-10.3]],"c":true},"ix":2},"nm":"Path 5","mn":"ADBE Vector Shape - Group","hd":false},{"ind":5,"ty":"sh","ix":6,"ks":{"a":0,"k":{"i":[[0,0.4],[-0.3,-0.5],[-0.5,-1.5],[1,-6.8],[0.7,-5.7],[0.1,-1.7],[1,-2.1],[0.4,2.6],[-0.1,2.5],[-0.4,1.1],[0.6,5.4],[0.4,1.4],[1,3.9]],"o":[[0.8,-0.3],[0.8,1.4],[2.1,6.4],[-0.8,5.7],[-0.2,1.8],[-0.1,1.5],[-1.1,-3.3],[-0.5,-2.5],[0,-1.2],[2,-5.1],[-0.2,-1.5],[-1.1,-3.9],[-0.1,-0.5]],"v":[[-24.05,-57],[-22.65,-56.2],[-20.55,-51.8],[-18.65,-32],[-20.95,-14.8],[-21.25,-9.5],[-22.35,-4.5],[-22.65,-13.1],[-23.05,-20.6],[-22.15,-24],[-20.15,-39.7],[-21.15,-44],[-24.15,-55.6]],"c":true},"ix":2},"nm":"Path 6","mn":"ADBE Vector Shape - Group","hd":false},{"ind":6,"ty":"sh","ix":7,"ks":{"a":0,"k":{"i":[[-3.3,-2.3],[3.1,4.6],[-1.1,2.3],[-1.3,-1.1],[-0.7,-0.9]],"o":[[-5.8,-1.1],[-1,-1.4],[1.8,0.4],[0.9,0.7],[2.5,3.2]],"v":[[-1.05,40.5],[-14.05,31.3],[-15.95,26.3],[-11.85,29.4],[-9.45,32]],"c":true},"ix":2},"nm":"Path 7","mn":"ADBE Vector Shape - Group","hd":false},{"ind":7,"ty":"sh","ix":8,"ks":{"a":0,"k":{"i":[[1.5,1.7],[2.9,1.8],[-3.1,-1.7],[-2.1,-2.6],[-1.5,-2.6],[0.8,0.1],[3,1.4]],"o":[[-1.9,-2.1],[3.8,-2.5],[2.9,1.6],[1.9,2.4],[-0.9,1.1],[-3.3,-0.5],[-2.1,-0.9]],"v":[[-4.15,32.3],[-10.25,25.9],[-0.45,25.7],[7.15,31.8],[12.85,39],[10.25,39.6],[0.95,36.6]],"c":true},"ix":2},"nm":"Path 8","mn":"ADBE Vector Shape - Group","hd":false},{"ind":8,"ty":"sh","ix":9,"ks":{"a":0,"k":{"i":[[-1.3,4.4],[-0.3,4.1],[-0.8,2.5],[-1.7,4.9],[-0.7,1.4],[-1.7,3],[-5.6,4],[-2.5,2.3],[-0.3,0.8],[-1.4,0.8],[0,-0.6],[0.1,-5.2],[0.6,-4.7],[0.3,-2.7],[4.3,-7.7],[5.4,-5.8],[0.9,-1],[3.1,0.4],[-0.3,-0.8],[1.4,-0.4],[0.7,-0.2],[0,1.6]],"o":[[1.1,-3.9],[0.2,-2.6],[1.5,-5],[0.5,-1.5],[1.6,-3],[3.3,-5.9],[2.8,-2],[0.6,-0.6],[0.6,-1.6],[1.1,0.5],[0,5.2],[0,4.8],[-0.3,2.6],[-0.9,8.9],[-3.9,6.9],[-0.9,1],[-2,2.2],[-0.8,-0.1],[0.6,1.9],[-0.6,0.2],[-0.7,-1.6],[-0.2,-4.4]],"v":[[-17.35,6.2],[-15.45,-5.7],[-13.75,-13.5],[-8.85,-28.3],[-6.55,-32.6],[-2.05,-41.8],[10.75,-57.1],[18.05,-64.3],[19.35,-66.6],[22.35,-70.2],[23.05,-68.3],[22.85,-52.7],[21.75,-38.5],[20.85,-30.5],[12.25,-5.8],[-1.55,13.4],[-4.35,16.3],[-11.75,19.5],[-13.25,20.7],[-15.15,23.5],[-16.95,24],[-18.45,19.4]],"c":true},"ix":2},"nm":"Path 9","mn":"ADBE Vector Shape - Group","hd":false},{"ind":9,"ty":"sh","ix":10,"ks":{"a":0,"k":{"i":[[1.4,3.8],[2.4,4.9],[0.1,2],[0.2,0.7],[0,0],[0.6,0.6],[2.2,0.8],[4.8,-0.4],[1.2,1],[-0.3,1.5],[1.3,7.5],[0.2,3.7],[-0.8,6.3],[1.8,-2.6],[3.3,-2.5],[4.1,-7.6],[1.1,-2.4],[1.8,-6.8],[0.1,-4.7],[1.1,-0.2],[-0.1,2.2],[-1.2,5.7],[0.9,6.8],[3.2,5.1],[0.9,0.5],[0.7,-1.7],[1.5,-5.8],[-0.5,-6.4],[1.2,-0.5],[3.3,1.8],[1.2,-0.9],[0.7,0.7],[1.1,1.4],[2.5,0.2],[2.9,-0.5],[-0.3,-3.2],[-0.2,-3.1],[-2,-4],[-0.6,-1.5],[0.3,-1.6],[1,-2.8],[-0.6,-3.4],[0,0],[-0.8,-0.7],[-2.7,-0.3],[0,0],[0,0],[-2.6,0.9],[-0.1,-1.5],[0,0],[-2,-0.6],[-3.6,-0.2],[-3.2,0.7],[0,0],[-2.3,0.2],[0,0],[-1.9,0.9],[0,0],[-1.6,1.6],[0,0],[-0.8,1.8],[0,0]],"o":[[-2,-5.2],[-0.9,-1.7],[0,-0.7],[0,0],[-0.5,-0.7],[-1.7,-1.5],[-4.4,-1.5],[-1.1,0.1],[0.2,-1.4],[1.4,-7.6],[-0.7,-3.7],[-0.3,-5.6],[-2.8,2.4],[-2.4,3.4],[-6.9,5.3],[-1.2,2.2],[-2.9,6.4],[-1.2,4.5],[0,0.5],[-0.4,-2.2],[0.2,-5.8],[1.3,-6.6],[-0.8,-6],[-0.5,-0.9],[-1.6,-0.8],[-2.2,5.5],[-1.6,6.2],[0.1,0.5],[-2.8,-2],[-1.4,-0.8],[-0.9,0.7],[-1.2,-1.4],[-1.5,-1.9],[-2.4,-0.1],[2.3,2.9],[0.3,3.1],[0.3,4.5],[0.7,1.5],[0.7,1.8],[-0.6,2.9],[-1.2,3.3],[-1.1,1.8],[0.8,0.7],[2,1.7],[2.7,14.4],[10.6,5.6],[0,0],[3.8,0.4],[0.2,6.3],[1.8,1],[0,0],[3.4,-0.7],[2.2,-1.7],[2.2,-0.2],[2.2,-0.2],[1.6,-1.3],[3.8,-0.6],[1.5,-1.7],[3.5,-1.6],[0.6,-1.5],[0,0],[-0.1,-4.2]],"v":[[65.35,20.1],[58.45,5.2],[56.75,-0.3],[56.35,-2.5],[50.85,-12.2],[49.25,-14.3],[44.05,-18.5],[30.45,-20.9],[26.95,-21.4],[27.55,-25.8],[27.65,-48.4],[26.25,-59.5],[26.45,-77.1],[19.55,-70],[11.35,-60.6],[-4.85,-41.2],[-8.35,-34.4],[-15.65,-14.7],[-18.15,-1.1],[-19.15,0.3],[-19.75,-6.2],[-17.65,-23.5],[-15.95,-43.4],[-21.55,-60.1],[-23.65,-62.3],[-26.85,-61.3],[-32.75,-44.4],[-34.65,-25.4],[-35.55,-23.7],[-44.85,-29.2],[-48.55,-29.2],[-50.95,-29.5],[-54.35,-33.6],[-60.35,-37.1],[-67.95,-36.9],[-64.45,-27.7],[-63.65,-18.4],[-59.95,-5.7],[-57.75,-1.3],[-59.25,3.2],[-61.65,11.8],[-62.45,21.9],[-58.45,30.5],[-56.15,32.6],[-50.95,38.7],[-46.35,56],[-30.05,62.4],[-27.35,62.3],[-19.05,64.1],[-9.95,71.7],[-4.45,74.7],[4.05,77.1],[13.95,74.9],[22.05,74.3],[28.75,73.6],[36.55,72.6],[42.05,69.8],[48.95,65.6],[53.55,60.7],[65.65,43.6],[67.75,38.8],[67.95,31.9]],"c":true},"ix":2},"nm":"Path 10","mn":"ADBE Vector Shape - Group","hd":false},{"ty":"mm","mm":1,"nm":"Merge Paths 1","mn":"ADBE Vector Filter - Merge","hd":false},{"ty":"fl","c":{"a":0,"k":[0.137254901961,0.121568634931,0.125490196078,1],"ix":4},"o":{"a":0,"k":100,"ix":5},"r":1,"bm":0,"nm":"Fill 1","mn":"ADBE Vector Graphic - Fill","hd":false},{"ty":"tr","p":{"a":0,"k":[68.2,77.35],"ix":2},"a":{"a":0,"k":[0,0],"ix":1},"s":{"a":0,"k":[100,100],"ix":3},"r":{"a":0,"k":0,"ix":6},"o":{"a":0,"k":100,"ix":7},"sk":{"a":0,"k":0,"ix":4},"sa":{"a":0,"k":0,"ix":5},"nm":"Transform"}],"nm":"Group 1","np":12,"cix":2,"bm":0,"ix":1,"mn":"ADBE Vector Group","hd":false},{"ty":"gr","it":[{"ind":0,"ty":"sh","ix":1,"ks":{"a":0,"k":{"i":[[0.6,-0.3],[2.5,0.6],[0.2,-1],[-0.5,-0.5],[-1.7,0.2],[-1.9,1.2],[0.3,0.8]],"o":[[-2.3,0.9],[-0.7,-0.2],[-0.2,0.9],[0.6,0.4],[1.3,-0.2],[0.6,-0.4],[-0.6,-1.4]],"v":[[3.3,-1.2],[-3.7,-0.4],[-5.5,0.4],[-4.3,2.1],[-1.2,2.5],[4.1,0.3],[5.4,-1.3]],"c":true},"ix":2},"nm":"Path 1","mn":"ADBE Vector Shape - Group","hd":false},{"ty":"fl","c":{"a":0,"k":[0.137254901961,0.121568634931,0.125490196078,1],"ix":4},"o":{"a":0,"k":100,"ix":5},"r":1,"bm":0,"nm":"Fill 1","mn":"ADBE Vector Graphic - Fill","hd":false},{"ty":"tr","p":{"a":0,"k":[107.75,128.75],"ix":2},"a":{"a":0,"k":[0,0],"ix":1},"s":{"a":0,"k":[100,100],"ix":3},"r":{"a":0,"k":0,"ix":6},"o":{"a":0,"k":100,"ix":7},"sk":{"a":0,"k":0,"ix":4},"sa":{"a":0,"k":0,"ix":5},"nm":"Transform"}],"nm":"Group 2","np":2,"cix":2,"bm":0,"ix":2,"mn":"ADBE Vector Group","hd":false},{"ty":"gr","it":[{"ind":0,"ty":"sh","ix":1,"ks":{"a":0,"k":{"i":[[0.2,0],[1.4,-0.7],[2,0.9],[0.6,0.3],[0.2,-0.5],[-0.2,-0.3],[-2.7,-0.4],[-2.5,0.9],[0,0.3]],"o":[[-1.5,-0.1],[-2.1,1],[-0.7,-0.3],[-0.4,-0.2],[-0.1,0.4],[1.4,2.2],[2.3,-0.8],[0.2,-0.1],[0,-0.2]],"v":[[6.5,-1.2],[2.1,-0.8],[-3.9,-1.2],[-5.8,-2.3],[-6.9,-2],[-6.9,-0.7],[-0.5,2.5],[6.8,0.1],[7.1,-0.7]],"c":true},"ix":2},"nm":"Path 1","mn":"ADBE Vector Shape - Group","hd":false},{"ty":"fl","c":{"a":0,"k":[0.137254901961,0.121568634931,0.125490196078,1],"ix":4},"o":{"a":0,"k":100,"ix":5},"r":1,"bm":0,"nm":"Fill 1","mn":"ADBE Vector Graphic - Fill","hd":false},{"ty":"tr","p":{"a":0,"k":[86.25,135.55],"ix":2},"a":{"a":0,"k":[0,0],"ix":1},"s":{"a":0,"k":[100,100],"ix":3},"r":{"a":0,"k":0,"ix":6},"o":{"a":0,"k":100,"ix":7},"sk":{"a":0,"k":0,"ix":4},"sa":{"a":0,"k":0,"ix":5},"nm":"Transform"}],"nm":"Group 3","np":2,"cix":2,"bm":0,"ix":3,"mn":"ADBE Vector Group","hd":false},{"ty":"gr","it":[{"ind":0,"ty":"sh","ix":1,"ks":{"a":0,"k":{"i":[[0.2,0],[1.1,-0.2],[0.9,3.9],[0.2,1.3],[1.6,1.6],[2.1,1.7],[0.1,-0.1],[-0.1,-0.3],[-1.2,-0.9],[-0.3,-3.8],[-0.8,-1.5],[-3.1,0],[-1.8,1.8],[0.1,0.2]],"o":[[-1.2,0.1],[-4,0.7],[-0.3,-1.3],[-0.3,-2.3],[-1.9,-1.9],[-0.2,-0.1],[-0.2,0.4],[0.5,1.5],[2.9,2.3],[0.1,1.7],[1.3,2.5],[1.8,-0.5],[0.2,-0.2],[-0.1,-0.2]],"v":[[10.4,7.85],[6.9,8.35],[0.1,3.95],[-0.8,0.05],[-3.8,-5.85],[-10,-10.95],[-10.8,-10.95],[-11.1,-9.75],[-8.1,-6.45],[-3,2.65],[-1.6,7.35],[4.9,11.05],[10.9,9.15],[11.1,8.35]],"c":true},"ix":2},"nm":"Path 1","mn":"ADBE Vector Shape - Group","hd":false},{"ty":"fl","c":{"a":0,"k":[0.137254901961,0.121568634931,0.125490196078,1],"ix":4},"o":{"a":0,"k":100,"ix":5},"r":1,"bm":0,"nm":"Fill 1","mn":"ADBE Vector Graphic - Fill","hd":false},{"ty":"tr","p":{"a":0,"k":[58.55,124.2],"ix":2},"a":{"a":0,"k":[0,0],"ix":1},"s":{"a":0,"k":[100,100],"ix":3},"r":{"a":0,"k":0,"ix":6},"o":{"a":0,"k":100,"ix":7},"sk":{"a":0,"k":0,"ix":4},"sa":{"a":0,"k":0,"ix":5},"nm":"Transform"}],"nm":"Group 4","np":2,"cix":2,"bm":0,"ix":4,"mn":"ADBE Vector Group","hd":false},{"ty":"gr","it":[{"ind":0,"ty":"sh","ix":1,"ks":{"a":0,"k":{"i":[[-0.3,0.5],[0.7,0.4],[2.3,0.6],[0.4,-0.6],[-0.2,-0.6],[-0.8,-0.2],[-1.2,-0.3]],"o":[[0.4,-0.9],[-2,-1.3],[-0.6,-0.2],[-0.4,0.5],[0.3,0.9],[1.8,0.6],[1.3,0.1]],"v":[[4.45,2.15],[3.45,0.55],[-2.85,-2.55],[-4.45,-2.15],[-4.55,-0.45],[-2.75,1.35],[2.15,2.65]],"c":true},"ix":2},"nm":"Path 1","mn":"ADBE Vector Shape - Group","hd":false},{"ty":"fl","c":{"a":0,"k":[0.137254901961,0.121568634931,0.125490196078,1],"ix":4},"o":{"a":0,"k":100,"ix":5},"r":1,"bm":0,"nm":"Fill 1","mn":"ADBE Vector Graphic - Fill","hd":false},{"ty":"tr","p":{"a":0,"k":[87,109.4],"ix":2},"a":{"a":0,"k":[0,0],"ix":1},"s":{"a":0,"k":[100,100],"ix":3},"r":{"a":0,"k":0,"ix":6},"o":{"a":0,"k":100,"ix":7},"sk":{"a":0,"k":0,"ix":4},"sa":{"a":0,"k":0,"ix":5},"nm":"Transform"}],"nm":"Group 5","np":2,"cix":2,"bm":0,"ix":5,"mn":"ADBE Vector Group","hd":false},{"ty":"gr","it":[{"ind":0,"ty":"sh","ix":1,"ks":{"a":0,"k":{"i":[[-1.6,-1.6],[0.4,-2.4],[-0.1,-0.1],[-0.9,-0.8],[-0.3,1.9],[-0.2,0.9],[2.1,2.1],[2.9,-2.1],[-0.1,-0.2],[-0.3,0.1],[-0.6,0.1]],"o":[[1.9,2.1],[0,0.3],[0.1,1],[0.5,0.5],[0.1,-0.9],[0.5,-3.1],[-2.4,-2.4],[-0.2,0.1],[0.1,0.2],[0.6,0],[2.1,-0.1]],"v":[[1.65,-2.8],[3.55,4.1],[3.55,4.7],[3.95,7.6],[5.55,4.8],[5.85,2.1],[2.85,-5.5],[-6.05,-6],[-6.25,-5.2],[-5.55,-4.9],[-3.75,-5.2]],"c":true},"ix":2},"nm":"Path 1","mn":"ADBE Vector Shape - Group","hd":false},{"ty":"fl","c":{"a":0,"k":[0.137254901961,0.121568634931,0.125490196078,1],"ix":4},"o":{"a":0,"k":100,"ix":5},"r":1,"bm":0,"nm":"Fill 1","mn":"ADBE Vector Graphic - Fill","hd":false},{"ty":"tr","p":{"a":0,"k":[103.9,96.75],"ix":2},"a":{"a":0,"k":[0,0],"ix":1},"s":{"a":0,"k":[100,100],"ix":3},"r":{"a":0,"k":0,"ix":6},"o":{"a":0,"k":100,"ix":7},"sk":{"a":0,"k":0,"ix":4},"sa":{"a":0,"k":0,"ix":5},"nm":"Transform"}],"nm":"Group 6","np":2,"cix":2,"bm":0,"ix":6,"mn":"ADBE Vector Group","hd":false},{"ty":"gr","it":[{"ind":0,"ty":"sh","ix":1,"ks":{"a":0,"k":{"i":[[1.3,-0.1],[0.7,0.5],[-0.2,0.9],[-0.7,-0.2],[-2.3,0.9],[-0.6,-1.4],[0.6,-0.4]],"o":[[-1.7,0.2],[-0.6,-0.4],[0.2,-1],[2.4,0.6],[0.6,-0.3],[0.3,0.8],[-1.9,1.1]],"v":[[-1.2,2.45],[-4.3,2.05],[-5.5,0.45],[-3.7,-0.35],[3.3,-1.15],[5.4,-1.25],[4.1,0.35]],"c":true},"ix":2},"nm":"Path 1","mn":"ADBE Vector Shape - Group","hd":false},{"ty":"fl","c":{"a":0,"k":[0.082352941176,0.082352941176,0.082352941176,1],"ix":4},"o":{"a":0,"k":100,"ix":5},"r":1,"bm":0,"nm":"Fill 1","mn":"ADBE Vector Graphic - Fill","hd":false},{"ty":"tr","p":{"a":0,"k":[107.75,128.7],"ix":2},"a":{"a":0,"k":[0,0],"ix":1},"s":{"a":0,"k":[100,100],"ix":3},"r":{"a":0,"k":0,"ix":6},"o":{"a":0,"k":100,"ix":7},"sk":{"a":0,"k":0,"ix":4},"sa":{"a":0,"k":0,"ix":5},"nm":"Transform"}],"nm":"Group 7","np":2,"cix":2,"bm":0,"ix":7,"mn":"ADBE Vector Group","hd":false},{"ty":"gr","it":[{"ind":0,"ty":"sh","ix":1,"ks":{"a":0,"k":{"i":[[1.2,0.1],[1.9,0.6],[0.3,0.9],[-0.4,0.6],[-0.6,-0.2],[-2,-1.3],[0.4,-0.9]],"o":[[-1.3,-0.3],[-0.8,-0.3],[-0.2,-0.6],[0.4,-0.6],[2.3,0.6],[0.6,0.4],[-0.3,0.6]],"v":[[2.25,2.65],[-2.75,1.35],[-4.55,-0.45],[-4.45,-2.15],[-2.85,-2.55],[3.45,0.55],[4.45,2.15]],"c":true},"ix":2},"nm":"Path 1","mn":"ADBE Vector Shape - Group","hd":false},{"ty":"fl","c":{"a":0,"k":[0.082352941176,0.082352941176,0.082352941176,1],"ix":4},"o":{"a":0,"k":100,"ix":5},"r":1,"bm":0,"nm":"Fill 1","mn":"ADBE Vector Graphic - Fill","hd":false},{"ty":"tr","p":{"a":0,"k":[87,109.3],"ix":2},"a":{"a":0,"k":[0,0],"ix":1},"s":{"a":0,"k":[100,100],"ix":3},"r":{"a":0,"k":0,"ix":6},"o":{"a":0,"k":100,"ix":7},"sk":{"a":0,"k":0,"ix":4},"sa":{"a":0,"k":0,"ix":5},"nm":"Transform"}],"nm":"Group 8","np":2,"cix":2,"bm":0,"ix":8,"mn":"ADBE Vector Group","hd":false},{"ty":"gr","it":[{"ind":0,"ty":"sh","ix":1,"ks":{"a":0,"k":{"i":[[2.3,-0.8],[1.5,2.2],[-0.1,0.4],[-0.4,-0.2],[-0.6,-0.3],[-2.1,1],[-1.5,-0.1],[-0.1,-0.1],[0.2,-0.1]],"o":[[-2.7,-0.4],[-0.2,-0.3],[0.2,-0.5],[0.7,0.3],[1.9,0.9],[1.4,-0.7],[0.2,0],[0,0.2],[-2.4,0.8]],"v":[[-0.5,2.45],[-6.9,-0.65],[-6.9,-1.95],[-5.8,-2.25],[-3.9,-1.15],[2.1,-0.75],[6.5,-1.15],[7.1,-0.75],[6.8,0.05]],"c":true},"ix":2},"nm":"Path 1","mn":"ADBE Vector Shape - Group","hd":false},{"ty":"fl","c":{"a":0,"k":[0.082352941176,0.082352941176,0.082352941176,1],"ix":4},"o":{"a":0,"k":100,"ix":5},"r":1,"bm":0,"nm":"Fill 1","mn":"ADBE Vector Graphic - Fill","hd":false},{"ty":"tr","p":{"a":0,"k":[86.25,135.5],"ix":2},"a":{"a":0,"k":[0,0],"ix":1},"s":{"a":0,"k":[100,100],"ix":3},"r":{"a":0,"k":0,"ix":6},"o":{"a":0,"k":100,"ix":7},"sk":{"a":0,"k":0,"ix":4},"sa":{"a":0,"k":0,"ix":5},"nm":"Transform"}],"nm":"Group 9","np":2,"cix":2,"bm":0,"ix":9,"mn":"ADBE Vector Group","hd":false},{"ty":"gr","it":[{"ind":0,"ty":"sh","ix":1,"ks":{"a":0,"k":{"i":[[0,0.4],[1.9,2.1],[2.3,-0.3],[0.6,-0.1],[0.1,0.1],[-0.2,0.1],[-2.4,-2.4],[0.4,-3.1],[0.1,-0.9],[0.5,0.4],[0.1,1]],"o":[[0.3,-2.4],[-1.5,-1.6],[-0.6,0.1],[-0.2,0],[-0.1,-0.2],[2.9,-2.1],[2.1,2.1],[-0.1,0.9],[-0.3,1.9],[-0.9,-0.9],[0.1,-0.2]],"v":[[3.75,4],[1.85,-2.9],[-3.75,-5.1],[-5.55,-4.8],[-6.25,-5.1],[-6.05,-5.9],[2.95,-5.5],[5.95,2.1],[5.65,4.8],[4.05,7.6],[3.65,4.7]],"c":true},"ix":2},"nm":"Path 1","mn":"ADBE Vector Shape - Group","hd":false},{"ty":"fl","c":{"a":0,"k":[0.082352941176,0.082352941176,0.082352941176,1],"ix":4},"o":{"a":0,"k":100,"ix":5},"r":1,"bm":0,"nm":"Fill 1","mn":"ADBE Vector Graphic - Fill","hd":false},{"ty":"tr","p":{"a":0,"k":[103.7,96.85],"ix":2},"a":{"a":0,"k":[0,0],"ix":1},"s":{"a":0,"k":[100,100],"ix":3},"r":{"a":0,"k":0,"ix":6},"o":{"a":0,"k":100,"ix":7},"sk":{"a":0,"k":0,"ix":4},"sa":{"a":0,"k":0,"ix":5},"nm":"Transform"}],"nm":"Group 10","np":2,"cix":2,"bm":0,"ix":10,"mn":"ADBE Vector Group","hd":false},{"ty":"gr","it":[{"ind":0,"ty":"sh","ix":1,"ks":{"a":0,"k":{"i":[[1.8,-0.5],[1.3,2.4],[0.2,1.7],[2.9,2.4],[0.6,1.5],[-0.2,0.4],[-0.2,-0.2],[-1.9,-1.8],[-0.3,-2.4],[-0.4,-1.3],[-4,0.7],[-1.2,0.1],[0,-0.2],[0.2,-0.2]],"o":[[-3.1,0],[-0.8,-1.5],[-0.4,-3.8],[-1.2,-0.9],[-0.1,-0.3],[0.1,-0.1],[2.1,1.6],[1.6,1.5],[0.2,1.3],[0.9,3.9],[1.2,-0.2],[0.2,0],[0.1,0.2],[-1.7,1.8]],"v":[[4.95,11.05],[-1.55,7.45],[-2.95,2.75],[-8.05,-6.35],[-11.05,-9.65],[-10.75,-10.85],[-9.95,-10.85],[-3.75,-5.85],[-0.75,0.05],[0.15,3.95],[6.95,8.35],[10.45,7.85],[11.05,8.35],[10.85,9.15]],"c":true},"ix":2},"nm":"Path 1","mn":"ADBE Vector Shape - Group","hd":false},{"ty":"fl","c":{"a":0,"k":[0.082352941176,0.082352941176,0.082352941176,1],"ix":4},"o":{"a":0,"k":100,"ix":5},"r":1,"bm":0,"nm":"Fill 1","mn":"ADBE Vector Graphic - Fill","hd":false},{"ty":"tr","p":{"a":0,"k":[58.5,124.2],"ix":2},"a":{"a":0,"k":[0,0],"ix":1},"s":{"a":0,"k":[100,100],"ix":3},"r":{"a":0,"k":0,"ix":6},"o":{"a":0,"k":100,"ix":7},"sk":{"a":0,"k":0,"ix":4},"sa":{"a":0,"k":0,"ix":5},"nm":"Transform"}],"nm":"Group 11","np":2,"cix":2,"bm":0,"ix":11,"mn":"ADBE Vector Group","hd":false},{"ty":"gr","it":[{"ind":0,"ty":"sh","ix":1,"ks":{"a":0,"k":{"i":[[0,0],[-3.2,-4.4],[-1.1,2.5],[-0.4,-9.2],[0.5,-6.1],[0,0],[0,0],[0,0],[-9.3,7.1],[0,0],[0,0],[2.5,-13.9],[6.9,-7],[0,0],[-4.4,-6.5],[4.4,-0.3],[0.7,5.4],[0,0],[0.7,1.8],[0.7,5.9],[0,0],[-0.5,0.6],[0,0],[-0.7,0.5],[-1.8,-2.8]],"o":[[7.2,-2.2],[-4.1,-25],[5.6,-0.3],[-2.2,10.4],[0,0],[0,0],[0,0],[5.4,-31.9],[0,0],[0,0],[1,5.7],[-2.5,13.9],[0,0],[6.3,-0.2],[-4.2,0.4],[-11,-2.3],[0,0],[-12.1,-1],[-9.8,-7.8],[0,0],[-1,0.4],[0,0],[0.4,-0.1],[2.9,-1.9],[0,0]],"v":[[-33.3,-12.6],[-14.9,-2.3],[-6.9,-47.4],[1.4,-20.3],[-2.9,11],[-3.2,14.5],[-2.7,18.9],[0.3,14.7],[34.9,-46.7],[44.6,-59.1],[44.9,-40.6],[44.8,-6.3],[20.8,32.2],[12.4,38.6],[33.5,57.9],[15.1,59.1],[-0.8,40.2],[-5,38.1],[-30,23.8],[-44.4,-3.7],[-46.3,-21.3],[-46.4,-22.3],[-46.3,-21.3],[-44.7,-22.2],[-35.6,-16.2]],"c":true},"ix":2},"nm":"Path 1","mn":"ADBE Vector Shape - Group","hd":false},{"ty":"st","c":{"a":0,"k":[0,0,0,1],"ix":3},"o":{"a":0,"k":100,"ix":4},"w":{"a":0,"k":1,"ix":5},"lc":1,"lj":1,"ml":4,"bm":0,"nm":"Stroke 1","mn":"ADBE Vector Graphic - Stroke","hd":false},{"ty":"fl","c":{"a":0,"k":[0.290196078431,0.819607902976,0.039215686275,1],"ix":4},"o":{"a":0,"k":100,"ix":5},"r":1,"bm":0,"nm":"Fill 1","mn":"ADBE Vector Graphic - Fill","hd":false},{"ty":"tr","p":{"a":0,"k":[49.95,60.55],"ix":2},"a":{"a":0,"k":[0,0],"ix":1},"s":{"a":0,"k":[100,100],"ix":3},"r":{"a":0,"k":0,"ix":6},"o":{"a":0,"k":100,"ix":7},"sk":{"a":0,"k":0,"ix":4},"sa":{"a":0,"k":0,"ix":5},"nm":"Transform"}],"nm":"Group 12","np":3,"cix":2,"bm":0,"ix":12,"mn":"ADBE Vector Group","hd":false},{"ty":"gr","it":[{"ind":0,"ty":"sh","ix":1,"ks":{"a":0,"k":{"i":[[3.2,3],[-3.5,7.4],[-3.3,-2],[-0.7,1.1],[0,0],[-3.8,-3.6],[0,0],[0,0],[6.2,3.7],[-6.9,12.6],[0,0],[-1.8,-11.6],[-2.5,-6.4],[-1.3,-5.4],[0.9,0],[1.9,-2.2],[0,0],[1.4,0.1],[3.6,-0.6],[5.1,1.2],[2.2,2.9],[2.8,3.5],[0,0]],"o":[[-3.3,-3.1],[18.3,17.8],[2.7,1.6],[0,0],[-1.7,4.1],[0,0],[0,0],[-0.9,-6.4],[9.3,-1.4],[0,0],[19.4,-6.8],[-0.2,-2],[3.2,8.2],[1.3,5.4],[-0.7,-0.1],[0,0],[-3.8,-0.3],[-1.7,-0.1],[-3.6,0.6],[-2,-0.5],[-11.6,-1.2],[0,0],[-3,-2.3]],"v":[[-61.9,1.45],[-57.1,-26.45],[-28.8,-2.05],[-23.4,-3.35],[-19.6,-0.05],[-10.6,14.85],[4.7,19.15],[11.4,14.25],[-9.3,-3.95],[22.9,-43.55],[24.6,-43.45],[55.9,-16.85],[61.3,-5.75],[63.9,14.25],[49.6,34.95],[43.1,43.35],[28.2,47.55],[17.6,48.65],[5.4,49.65],[-9.1,48.55],[-22.4,38.25],[-49.1,29.55],[-52.9,13.55]],"c":true},"ix":2},"nm":"Path 1","mn":"ADBE Vector Shape - Group","hd":false},{"ty":"fl","c":{"a":0,"k":[0.917647118662,0.160784313725,0.160784313725,1],"ix":4},"o":{"a":0,"k":100,"ix":5},"r":1,"bm":0,"nm":"Fill 1","mn":"ADBE Vector Graphic - Fill","hd":false},{"ty":"tr","p":{"a":0,"k":[70.55,101.5],"ix":2},"a":{"a":0,"k":[0,0],"ix":1},"s":{"a":0,"k":[100,100],"ix":3},"r":{"a":0,"k":0,"ix":6},"o":{"a":0,"k":100,"ix":7},"sk":{"a":0,"k":0,"ix":4},"sa":{"a":0,"k":0,"ix":5},"nm":"Transform"}],"nm":"Group 13","np":2,"cix":2,"bm":0,"ix":13,"mn":"ADBE Vector Group","hd":false}],"ip":0,"op":450.000018328876,"st":0,"bm":0}]},{"id":"comp_1","layers":[{"ddd":0,"ind":1,"ty":4,"nm":"색 ㅌ 일러/Since1976 Outlines","sr":1,"ks":{"o":{"a":0,"k":100,"ix":11},"r":{"a":0,"k":0,"ix":10},"p":{"a":0,"k":[245,293,0],"ix":2},"a":{"a":0,"k":[245,293,0],"ix":1},"s":{"a":0,"k":[100,100,100],"ix":6}},"ao":0,"shapes":[{"ty":"gr","it":[{"ind":0,"ty":"sh","ix":1,"ks":{"a":0,"k":{"i":[[1.4,-4.9],[0.8,-2.1],[2.9,-2.8],[2.3,-1.7],[0.2,-0.3],[5.9,-1.8],[3.9,-0.5],[0.4,-0.2],[2.1,-1.3],[2.1,-0.5],[4.5,2.9],[1.1,0.5],[1.6,4],[1.1,1],[0,-0.8],[1.8,1.3],[6.9,4.2],[2.1,0.1],[1.5,1.1],[1.2,1.9],[-0.7,2.9],[-1.6,4.2],[-0.1,0.7],[-0.3,-0.5],[-1.7,-2.1],[-8.4,-3],[-2.9,0.4],[0,-1],[-3.6,-3.5],[-5.2,-0.6],[-2.4,0.2],[-1.3,1.6],[-1,-0.1],[-1,-0.2],[0.4,1.1],[0.2,0.7],[0.5,-0.1],[1.2,1.5],[1.4,1.9],[3.4,1.7],[0.4,0.2],[-2.4,1.8],[-1.9,1.6],[-1.6,2.6],[-1.3,2],[-2,5.9],[0,0.1],[-2.8,-0.5],[-4.2,-1.6],[-0.7,-0.8],[-1,-6.7],[-1.6,-3],[-1.3,-3.7]],"o":[[-0.6,2.2],[-1.4,3.6],[-2,2],[-0.2,0.2],[-3.1,6.1],[-4,-0.2],[-0.4,0.1],[-2.2,0.5],[-1.9,1.1],[-5.2,1.3],[-1,-0.7],[-4,-1.9],[-0.6,-1.5],[-2.1,-0.6],[-1.6,-1.6],[-6.1,-1.5],[-1.8,-1.1],[-1.9,-0.2],[-1.8,-1.4],[-1.5,-2.2],[1,-4.3],[0.3,-0.7],[0.1,-0.6],[1.7,2.1],[5.5,7.3],[2.7,1],[0.8,-0.1],[0.2,5.3],[3.8,3.7],[2.4,0.3],[1.8,-0.2],[0.7,-0.9],[1,0.1],[1.2,0.3],[-0.3,-0.7],[-0.1,-0.5],[-2.3,0.2],[-1.6,-1.8],[-2.2,-3.1],[-0.4,-0.2],[-2.7,-1.5],[2,-1.6],[2.3,-2],[1.3,-2],[3.4,-5.1],[0.1,-0.1],[0.7,-2.5],[4.5,-0.4],[0.9,0.4],[4.5,4.7],[0.5,3.4],[1.9,3.4],[1.9,4.3]],"v":[[64.45,37.2],[62.75,43.7],[56.65,53.5],[50.75,59.6],[50.15,60.3],[35.35,70],[23.65,71.7],[22.35,71.9],[15.85,71.8],[9.75,73.4],[-4.75,71.1],[-7.95,69.4],[-16.45,65.3],[-19.25,61.4],[-21.35,61.5],[-30.15,59.8],[-44.85,55.1],[-50.95,36.2],[-53.75,30.6],[-58.35,25.7],[-59.95,18.1],[-56.65,5.2],[-56.25,3],[-54.95,2.6],[-49.75,8.8],[-28.45,23.7],[-20.05,24.4],[-18.55,25.6],[-12.05,38.4],[1.45,44.7],[8.65,44.9],[13.55,43.1],[16.45,42.4],[19.45,43.2],[20.85,41.8],[20.05,39.7],[19.25,38.9],[14.55,36],[9.95,30.5],[1.55,23.3],[0.35,22.7],[0.05,19.3],[5.85,14.4],[11.65,7.6],[15.65,1.7],[24.45,-14.3],[24.55,-14.7],[29.65,-17.9],[42.55,-15],[45.15,-13.2],[54.55,3.2],[58.35,12.7],[63.35,23.2]],"c":true},"ix":2},"nm":"Path 1","mn":"ADBE Vector Shape - Group","hd":false},{"ind":1,"ty":"sh","ix":2,"ks":{"a":0,"k":{"i":[[1.8,5.1],[0.1,3],[0.1,3.5],[-2.5,-2.6],[-1.4,-4],[-0.8,-3.2],[-2.7,-4.4],[-0.9,-1.4],[3.3,5.2],[1.1,1.2]],"o":[[-1,-2.8],[-0.1,-2.5],[3.4,3.3],[3,3.1],[1.1,3.1],[1.3,4.9],[0.8,1.3],[-4.9,-3.1],[-0.9,-1.4],[-3.8,-4.1]],"v":[[-58.65,-11.3],[-61.15,-19.8],[-61.35,-28.3],[-52.55,-20.3],[-46.05,-9.7],[-43.15,-0.3],[-36.65,13.4],[-33.75,17.2],[-47.35,6.3],[-50.45,2.5]],"c":true},"ix":2},"nm":"Path 2","mn":"ADBE Vector Shape - Group","hd":false},{"ind":2,"ty":"sh","ix":3,"ks":{"a":0,"k":{"i":[[-0.1,0.2],[-0.4,-0.2],[-0.7,-2.5],[1.6,1.7]],"o":[[0.3,-0.5],[2.1,1.2],[-2.2,-1.1],[-0.1,-0.2]],"v":[[-60.75,-33.3],[-59.55,-33.4],[-55.25,-27.9],[-60.65,-32.5]],"c":true},"ix":2},"nm":"Path 3","mn":"ADBE Vector Shape - Group","hd":false},{"ind":3,"ty":"sh","ix":4,"ks":{"a":0,"k":{"i":[[-0.4,0.1],[-2.6,-1.6],[-2.3,-3.6],[-2.5,-5.5],[-0.6,-3.8],[0,-0.4],[3.1,0.7],[1.8,2.9],[1,5.1],[2.9,4.9],[2.1,2.6]],"o":[[3.2,-1.3],[3.6,2.2],[3.3,5.2],[1.6,3.6],[0.1,0.4],[-0.2,3],[-3.4,-0.7],[-2.7,-4.3],[-1.1,-5.6],[-1.4,-2.4],[0.8,0]],"v":[[-50.85,-25.5],[-42.55,-23.8],[-33.85,-14.9],[-25.35,1.2],[-22.65,12.4],[-22.65,13.7],[-26.65,16.4],[-34.45,10.9],[-40.65,-2.8],[-46.95,-18.4],[-52.55,-25.4]],"c":true},"ix":2},"nm":"Path 4","mn":"ADBE Vector Shape - Group","hd":false},{"ind":4,"ty":"sh","ix":5,"ks":{"a":0,"k":{"i":[[0,7.9],[-1.7,6.3],[-1.6,0.3],[-0.9,-5.8],[0.7,-2.3],[-0.6,-6.2],[0.2,-0.3]],"o":[[0,-6.7],[0.2,-0.9],[1.7,5.7],[0.4,2.4],[-1.8,5.9],[0,0.2],[-5.3,-6.2]],"v":[[-32.55,-31.7],[-28.95,-50.9],[-27.05,-53.4],[-22.75,-36.3],[-23.55,-29.2],[-25.55,-11.1],[-25.95,-10.3]],"c":true},"ix":2},"nm":"Path 5","mn":"ADBE Vector Shape - Group","hd":false},{"ind":5,"ty":"sh","ix":6,"ks":{"a":0,"k":{"i":[[0,0.4],[-0.3,-0.5],[-0.5,-1.5],[1,-6.8],[0.7,-5.7],[0.1,-1.7],[1,-2.1],[0.4,2.6],[-0.1,2.5],[-0.4,1.1],[0.7,5.4],[0.4,1.4],[0.9,3.9]],"o":[[0.8,-0.3],[0.8,1.4],[2.1,6.4],[-0.8,5.7],[-0.2,1.8],[-0.1,1.5],[-1.1,-3.3],[-0.5,-2.5],[0.1,-1.2],[2,-5.1],[-0.2,-1.5],[-1.1,-3.9],[0,-0.5]],"v":[[-24.05,-57],[-22.65,-56.2],[-20.55,-51.8],[-18.65,-32],[-20.95,-14.8],[-21.25,-9.5],[-22.35,-4.5],[-22.65,-13.1],[-23.05,-20.6],[-22.15,-24],[-20.25,-39.7],[-21.25,-44],[-24.25,-55.6]],"c":true},"ix":2},"nm":"Path 6","mn":"ADBE Vector Shape - Group","hd":false},{"ind":6,"ty":"sh","ix":7,"ks":{"a":0,"k":{"i":[[-3.3,-2.3],[3.1,4.6],[-1.1,2.3],[-1.3,-1.1],[-0.7,-0.9]],"o":[[-5.8,-1.1],[-1,-1.4],[1.8,0.4],[0.9,0.7],[2.5,3.2]],"v":[[-1.05,40.5],[-14.05,31.3],[-15.95,26.3],[-11.85,29.4],[-9.45,32]],"c":true},"ix":2},"nm":"Path 7","mn":"ADBE Vector Shape - Group","hd":false},{"ind":7,"ty":"sh","ix":8,"ks":{"a":0,"k":{"i":[[1.5,1.7],[2.9,1.8],[-3.1,-1.7],[-2.1,-2.6],[-1.5,-2.6],[0.8,0.1],[3,1.4]],"o":[[-1.9,-2.1],[3.8,-2.5],[2.9,1.6],[1.9,2.4],[-0.9,1.1],[-3.3,-0.5],[-2.1,-0.9]],"v":[[-4.15,32.3],[-10.25,25.9],[-0.45,25.7],[7.15,31.8],[12.85,39],[10.25,39.6],[0.95,36.6]],"c":true},"ix":2},"nm":"Path 8","mn":"ADBE Vector Shape - Group","hd":false},{"ind":8,"ty":"sh","ix":9,"ks":{"a":0,"k":{"i":[[-1.3,4.4],[-0.3,4.1],[-0.8,2.5],[-1.7,4.9],[-0.7,1.4],[-1.7,3],[-5.6,4],[-2.5,2.3],[-0.3,0.8],[-1.4,0.8],[0,-0.6],[0.1,-5.2],[0.6,-4.7],[0.3,-2.7],[4.3,-7.7],[5.4,-5.8],[0.9,-1],[3.1,0.4],[-0.3,-0.8],[1.4,-0.4],[0.7,-0.2],[0,1.6]],"o":[[1.1,-3.9],[0.2,-2.6],[1.5,-5],[0.5,-1.5],[1.6,-3],[3.3,-5.9],[2.8,-2],[0.6,-0.6],[0.6,-1.6],[1.1,0.5],[0,5.2],[0,4.8],[-0.3,2.6],[-0.9,8.9],[-3.9,6.9],[-0.9,1],[-2,2.2],[-0.8,-0.1],[0.6,1.9],[-0.6,0.2],[-0.7,-1.6],[-0.2,-4.4]],"v":[[-17.35,6.2],[-15.45,-5.7],[-13.75,-13.5],[-8.85,-28.3],[-6.55,-32.6],[-2.05,-41.8],[10.75,-57.1],[18.05,-64.3],[19.35,-66.6],[22.35,-70.2],[23.05,-68.3],[22.85,-52.7],[21.75,-38.5],[20.85,-30.5],[12.25,-5.8],[-1.55,13.4],[-4.35,16.3],[-11.75,19.5],[-13.25,20.7],[-15.15,23.5],[-16.95,24],[-18.45,19.4]],"c":true},"ix":2},"nm":"Path 9","mn":"ADBE Vector Shape - Group","hd":false},{"ind":9,"ty":"sh","ix":10,"ks":{"a":0,"k":{"i":[[1.4,3.8],[2.4,4.9],[0.1,2],[0.2,0.7],[0,0],[0.6,0.6],[2.2,0.8],[4.8,-0.4],[1.2,1],[-0.3,1.5],[1.3,7.5],[0.2,3.7],[-0.8,6.3],[1.8,-2.6],[3.3,-2.5],[4.1,-7.6],[1.1,-2.4],[1.8,-6.8],[0.1,-4.7],[1.1,-0.2],[-0.1,2.2],[-1.2,5.7],[0.9,6.8],[3.2,5.1],[0.9,0.5],[0.7,-1.7],[1.5,-5.8],[-0.5,-6.4],[1.2,-0.5],[3.2,1.8],[1.2,-0.9],[0.7,0.7],[1.1,1.4],[2.5,0.2],[2.9,-0.5],[-0.3,-3.2],[-0.2,-3.1],[-2,-4],[-0.6,-1.5],[0.3,-1.6],[1,-2.8],[-0.6,-3.4],[0,0],[-0.8,-0.7],[-2.7,-0.3],[0,0],[0,0],[-2.6,0.9],[-0.1,-1.5],[0,0],[-2,-0.6],[-3.6,-0.2],[-3.2,0.7],[0,0],[-2.3,0.2],[0,0],[-1.9,0.9],[0,0],[-1.6,1.6],[0,0],[-0.8,1.8],[0,0]],"o":[[-2,-5.2],[-0.9,-1.7],[0,-0.7],[0,0],[-0.5,-0.7],[-1.7,-1.5],[-4.4,-1.5],[-1.1,0.1],[0.2,-1.4],[1.4,-7.6],[-0.7,-3.7],[-0.3,-5.6],[-2.8,2.4],[-2.4,3.4],[-6.9,5.3],[-1.2,2.2],[-2.9,6.4],[-1.2,4.5],[0,0.5],[-0.4,-2.2],[0.2,-5.8],[1.3,-6.6],[-0.8,-6],[-0.5,-0.9],[-1.6,-0.8],[-2.2,5.5],[-1.6,6.2],[0.1,0.5],[-2.8,-2],[-1.4,-0.8],[-0.9,0.7],[-1.2,-1.4],[-1.5,-1.9],[-2.4,-0.1],[2.3,2.9],[0.3,3.1],[0.3,4.5],[0.7,1.5],[0.7,1.8],[-0.6,2.9],[-1.2,3.3],[-1.1,1.8],[0.8,0.7],[2,1.7],[2.7,14.4],[10.6,5.6],[0,0],[3.8,0.4],[0.2,6.3],[1.8,1],[0,0],[3.4,-0.7],[2.2,-1.7],[2.2,-0.2],[2.2,-0.2],[1.6,-1.3],[3.8,-0.6],[1.5,-1.7],[3.5,-1.6],[0.6,-1.5],[0,0],[-0.1,-4.2]],"v":[[65.35,20.1],[58.45,5.2],[56.75,-0.3],[56.35,-2.5],[50.85,-12.2],[49.25,-14.3],[44.05,-18.5],[30.45,-20.9],[26.95,-21.4],[27.55,-25.8],[27.65,-48.4],[26.25,-59.5],[26.45,-77.1],[19.55,-70],[11.35,-60.6],[-4.85,-41.2],[-8.35,-34.4],[-15.65,-14.7],[-18.15,-1.1],[-19.15,0.3],[-19.75,-6.2],[-17.65,-23.5],[-15.95,-43.4],[-21.55,-60.1],[-23.65,-62.3],[-26.85,-61.3],[-32.75,-44.4],[-34.65,-25.4],[-35.55,-23.7],[-44.85,-29.2],[-48.55,-29.2],[-50.95,-29.5],[-54.35,-33.6],[-60.35,-37.1],[-67.95,-36.9],[-64.45,-27.7],[-63.65,-18.4],[-59.95,-5.7],[-57.75,-1.3],[-59.25,3.2],[-61.65,11.8],[-62.45,21.9],[-58.45,30.5],[-56.15,32.6],[-50.95,38.7],[-46.35,56],[-30.05,62.4],[-27.35,62.3],[-19.05,64.1],[-9.95,71.7],[-4.45,74.7],[4.05,77.1],[13.95,74.9],[22.05,74.3],[28.75,73.6],[36.55,72.6],[42.05,69.8],[48.95,65.6],[53.55,60.7],[65.65,43.6],[67.75,38.8],[67.95,31.9]],"c":true},"ix":2},"nm":"Path 10","mn":"ADBE Vector Shape - Group","hd":false},{"ty":"mm","mm":1,"nm":"Merge Paths 1","mn":"ADBE Vector Filter - Merge","hd":false},{"ty":"fl","c":{"a":0,"k":[0.137254901961,0.121568634931,0.125490196078,1],"ix":4},"o":{"a":0,"k":100,"ix":5},"r":1,"bm":0,"nm":"Fill 1","mn":"ADBE Vector Graphic - Fill","hd":false},{"ty":"tr","p":{"a":0,"k":[68.2,494.1],"ix":2},"a":{"a":0,"k":[0,0],"ix":1},"s":{"a":0,"k":[100,100],"ix":3},"r":{"a":0,"k":0,"ix":6},"o":{"a":0,"k":100,"ix":7},"sk":{"a":0,"k":0,"ix":4},"sa":{"a":0,"k":0,"ix":5},"nm":"Transform"}],"nm":"Group 1","np":12,"cix":2,"bm":0,"ix":1,"mn":"ADBE Vector Group","hd":false},{"ty":"gr","it":[{"ind":0,"ty":"sh","ix":1,"ks":{"a":0,"k":{"i":[[0.6,-0.3],[2.5,0.6],[0.2,-1],[-0.5,-0.5],[-1.7,0.2],[-1.9,1.2],[0.3,0.8]],"o":[[-2.3,0.9],[-0.7,-0.2],[-0.2,0.9],[0.6,0.4],[1.3,-0.2],[0.6,-0.4],[-0.6,-1.4]],"v":[[3.3,-1.2],[-3.7,-0.4],[-5.5,0.4],[-4.3,2.1],[-1.2,2.5],[4.1,0.3],[5.4,-1.3]],"c":true},"ix":2},"nm":"Path 1","mn":"ADBE Vector Shape - Group","hd":false},{"ty":"fl","c":{"a":0,"k":[0.137254901961,0.121568634931,0.125490196078,1],"ix":4},"o":{"a":0,"k":100,"ix":5},"r":1,"bm":0,"nm":"Fill 1","mn":"ADBE Vector Graphic - Fill","hd":false},{"ty":"tr","p":{"a":0,"k":[107.75,545.5],"ix":2},"a":{"a":0,"k":[0,0],"ix":1},"s":{"a":0,"k":[100,100],"ix":3},"r":{"a":0,"k":0,"ix":6},"o":{"a":0,"k":100,"ix":7},"sk":{"a":0,"k":0,"ix":4},"sa":{"a":0,"k":0,"ix":5},"nm":"Transform"}],"nm":"Group 2","np":2,"cix":2,"bm":0,"ix":2,"mn":"ADBE Vector Group","hd":false},{"ty":"gr","it":[{"ind":0,"ty":"sh","ix":1,"ks":{"a":0,"k":{"i":[[0.2,0],[1.4,-0.7],[2,0.9],[0.6,0.3],[0.2,-0.5],[-0.2,-0.3],[-2.7,-0.4],[-2.5,0.9],[0,0.3]],"o":[[-1.5,-0.1],[-2.1,1],[-0.7,-0.3],[-0.4,-0.2],[-0.1,0.4],[1.4,2.2],[2.3,-0.8],[0.2,-0.1],[0,-0.2]],"v":[[6.5,-1.2],[2.1,-0.8],[-3.9,-1.2],[-5.8,-2.3],[-6.9,-2],[-6.9,-0.7],[-0.5,2.5],[6.8,0.1],[7.1,-0.7]],"c":true},"ix":2},"nm":"Path 1","mn":"ADBE Vector Shape - Group","hd":false},{"ty":"fl","c":{"a":0,"k":[0.137254901961,0.121568634931,0.125490196078,1],"ix":4},"o":{"a":0,"k":100,"ix":5},"r":1,"bm":0,"nm":"Fill 1","mn":"ADBE Vector Graphic - Fill","hd":false},{"ty":"tr","p":{"a":0,"k":[86.25,552.3],"ix":2},"a":{"a":0,"k":[0,0],"ix":1},"s":{"a":0,"k":[100,100],"ix":3},"r":{"a":0,"k":0,"ix":6},"o":{"a":0,"k":100,"ix":7},"sk":{"a":0,"k":0,"ix":4},"sa":{"a":0,"k":0,"ix":5},"nm":"Transform"}],"nm":"Group 3","np":2,"cix":2,"bm":0,"ix":3,"mn":"ADBE Vector Group","hd":false},{"ty":"gr","it":[{"ind":0,"ty":"sh","ix":1,"ks":{"a":0,"k":{"i":[[0.2,0],[1.1,-0.2],[0.9,3.9],[0.2,1.3],[1.6,1.6],[2.1,1.7],[0.1,-0.1],[-0.1,-0.3],[-1.2,-0.9],[-0.3,-3.8],[-0.8,-1.5],[-3.1,0],[-1.8,1.8],[0.1,0.2]],"o":[[-1.2,0.1],[-4,0.7],[-0.3,-1.3],[-0.3,-2.3],[-1.9,-1.9],[-0.2,-0.1],[-0.2,0.4],[0.5,1.5],[2.9,2.3],[0.1,1.7],[1.3,2.5],[1.8,-0.5],[0.2,-0.2],[-0.1,-0.2]],"v":[[10.4,7.85],[6.9,8.35],[0.1,3.95],[-0.8,0.05],[-3.8,-5.85],[-10,-10.95],[-10.8,-10.95],[-11.1,-9.75],[-8.1,-6.45],[-3,2.65],[-1.6,7.35],[4.9,11.05],[10.9,9.15],[11.1,8.35]],"c":true},"ix":2},"nm":"Path 1","mn":"ADBE Vector Shape - Group","hd":false},{"ty":"fl","c":{"a":0,"k":[0.137254901961,0.121568634931,0.125490196078,1],"ix":4},"o":{"a":0,"k":100,"ix":5},"r":1,"bm":0,"nm":"Fill 1","mn":"ADBE Vector Graphic - Fill","hd":false},{"ty":"tr","p":{"a":0,"k":[58.55,540.95],"ix":2},"a":{"a":0,"k":[0,0],"ix":1},"s":{"a":0,"k":[100,100],"ix":3},"r":{"a":0,"k":0,"ix":6},"o":{"a":0,"k":100,"ix":7},"sk":{"a":0,"k":0,"ix":4},"sa":{"a":0,"k":0,"ix":5},"nm":"Transform"}],"nm":"Group 4","np":2,"cix":2,"bm":0,"ix":4,"mn":"ADBE Vector Group","hd":false},{"ty":"gr","it":[{"ind":0,"ty":"sh","ix":1,"ks":{"a":0,"k":{"i":[[-0.3,0.5],[0.7,0.4],[2.3,0.6],[0.4,-0.6],[-0.2,-0.6],[-0.8,-0.2],[-1.2,-0.3]],"o":[[0.4,-0.9],[-2,-1.3],[-0.6,-0.2],[-0.4,0.5],[0.3,0.9],[1.8,0.6],[1.3,0.1]],"v":[[4.45,2.15],[3.45,0.55],[-2.85,-2.55],[-4.45,-2.15],[-4.55,-0.45],[-2.75,1.35],[2.15,2.65]],"c":true},"ix":2},"nm":"Path 1","mn":"ADBE Vector Shape - Group","hd":false},{"ty":"fl","c":{"a":0,"k":[0.137254901961,0.121568634931,0.125490196078,1],"ix":4},"o":{"a":0,"k":100,"ix":5},"r":1,"bm":0,"nm":"Fill 1","mn":"ADBE Vector Graphic - Fill","hd":false},{"ty":"tr","p":{"a":0,"k":[87,526.15],"ix":2},"a":{"a":0,"k":[0,0],"ix":1},"s":{"a":0,"k":[100,100],"ix":3},"r":{"a":0,"k":0,"ix":6},"o":{"a":0,"k":100,"ix":7},"sk":{"a":0,"k":0,"ix":4},"sa":{"a":0,"k":0,"ix":5},"nm":"Transform"}],"nm":"Group 5","np":2,"cix":2,"bm":0,"ix":5,"mn":"ADBE Vector Group","hd":false},{"ty":"gr","it":[{"ind":0,"ty":"sh","ix":1,"ks":{"a":0,"k":{"i":[[-1.6,-1.6],[0.4,-2.4],[-0.1,-0.1],[-0.9,-0.8],[-0.3,1.9],[-0.2,0.9],[2.1,2.1],[2.9,-2.1],[-0.1,-0.2],[-0.3,0.1],[-0.6,0.1]],"o":[[1.9,2.1],[0,0.3],[0.1,1],[0.5,0.5],[0.1,-0.9],[0.5,-3.1],[-2.4,-2.4],[-0.2,0.1],[0.1,0.2],[0.6,0],[2.1,-0.1]],"v":[[1.65,-2.8],[3.55,4.1],[3.55,4.7],[3.95,7.6],[5.55,4.8],[5.85,2.1],[2.85,-5.5],[-6.05,-6],[-6.25,-5.2],[-5.55,-4.9],[-3.75,-5.2]],"c":true},"ix":2},"nm":"Path 1","mn":"ADBE Vector Shape - Group","hd":false},{"ty":"fl","c":{"a":0,"k":[0.137254901961,0.121568634931,0.125490196078,1],"ix":4},"o":{"a":0,"k":100,"ix":5},"r":1,"bm":0,"nm":"Fill 1","mn":"ADBE Vector Graphic - Fill","hd":false},{"ty":"tr","p":{"a":0,"k":[103.9,513.5],"ix":2},"a":{"a":0,"k":[0,0],"ix":1},"s":{"a":0,"k":[100,100],"ix":3},"r":{"a":0,"k":0,"ix":6},"o":{"a":0,"k":100,"ix":7},"sk":{"a":0,"k":0,"ix":4},"sa":{"a":0,"k":0,"ix":5},"nm":"Transform"}],"nm":"Group 6","np":2,"cix":2,"bm":0,"ix":6,"mn":"ADBE Vector Group","hd":false},{"ty":"gr","it":[{"ind":0,"ty":"sh","ix":1,"ks":{"a":0,"k":{"i":[[1.3,-0.1],[0.7,0.5],[-0.2,0.9],[-0.7,-0.2],[-2.3,0.9],[-0.6,-1.4],[0.6,-0.4]],"o":[[-1.7,0.2],[-0.6,-0.4],[0.2,-1],[2.4,0.6],[0.6,-0.3],[0.3,0.8],[-1.9,1.1]],"v":[[-1.2,2.45],[-4.3,2.05],[-5.5,0.45],[-3.7,-0.35],[3.3,-1.15],[5.4,-1.25],[4.1,0.35]],"c":true},"ix":2},"nm":"Path 1","mn":"ADBE Vector Shape - Group","hd":false},{"ty":"fl","c":{"a":0,"k":[0.082352941176,0.082352941176,0.082352941176,1],"ix":4},"o":{"a":0,"k":100,"ix":5},"r":1,"bm":0,"nm":"Fill 1","mn":"ADBE Vector Graphic - Fill","hd":false},{"ty":"tr","p":{"a":0,"k":[107.75,545.45],"ix":2},"a":{"a":0,"k":[0,0],"ix":1},"s":{"a":0,"k":[100,100],"ix":3},"r":{"a":0,"k":0,"ix":6},"o":{"a":0,"k":100,"ix":7},"sk":{"a":0,"k":0,"ix":4},"sa":{"a":0,"k":0,"ix":5},"nm":"Transform"}],"nm":"Group 7","np":2,"cix":2,"bm":0,"ix":7,"mn":"ADBE Vector Group","hd":false},{"ty":"gr","it":[{"ind":0,"ty":"sh","ix":1,"ks":{"a":0,"k":{"i":[[1.2,0.1],[1.9,0.6],[0.3,0.9],[-0.4,0.6],[-0.6,-0.2],[-2,-1.3],[0.4,-0.9]],"o":[[-1.3,-0.3],[-0.8,-0.3],[-0.2,-0.6],[0.4,-0.6],[2.3,0.6],[0.6,0.4],[-0.3,0.6]],"v":[[2.25,2.65],[-2.75,1.35],[-4.55,-0.45],[-4.45,-2.15],[-2.85,-2.55],[3.45,0.55],[4.45,2.15]],"c":true},"ix":2},"nm":"Path 1","mn":"ADBE Vector Shape - Group","hd":false},{"ty":"fl","c":{"a":0,"k":[0.082352941176,0.082352941176,0.082352941176,1],"ix":4},"o":{"a":0,"k":100,"ix":5},"r":1,"bm":0,"nm":"Fill 1","mn":"ADBE Vector Graphic - Fill","hd":false},{"ty":"tr","p":{"a":0,"k":[87,526.05],"ix":2},"a":{"a":0,"k":[0,0],"ix":1},"s":{"a":0,"k":[100,100],"ix":3},"r":{"a":0,"k":0,"ix":6},"o":{"a":0,"k":100,"ix":7},"sk":{"a":0,"k":0,"ix":4},"sa":{"a":0,"k":0,"ix":5},"nm":"Transform"}],"nm":"Group 8","np":2,"cix":2,"bm":0,"ix":8,"mn":"ADBE Vector Group","hd":false},{"ty":"gr","it":[{"ind":0,"ty":"sh","ix":1,"ks":{"a":0,"k":{"i":[[2.3,-0.8],[1.5,2.2],[-0.1,0.4],[-0.4,-0.2],[-0.6,-0.3],[-2.1,1],[-1.5,-0.1],[-0.1,-0.1],[0.2,-0.1]],"o":[[-2.7,-0.4],[-0.2,-0.3],[0.2,-0.5],[0.7,0.3],[1.9,0.9],[1.4,-0.7],[0.2,0],[0,0.2],[-2.4,0.8]],"v":[[-0.5,2.45],[-6.9,-0.65],[-6.9,-1.95],[-5.8,-2.25],[-3.9,-1.15],[2.1,-0.75],[6.5,-1.15],[7.1,-0.75],[6.8,0.05]],"c":true},"ix":2},"nm":"Path 1","mn":"ADBE Vector Shape - Group","hd":false},{"ty":"fl","c":{"a":0,"k":[0.082352941176,0.082352941176,0.082352941176,1],"ix":4},"o":{"a":0,"k":100,"ix":5},"r":1,"bm":0,"nm":"Fill 1","mn":"ADBE Vector Graphic - Fill","hd":false},{"ty":"tr","p":{"a":0,"k":[86.25,552.25],"ix":2},"a":{"a":0,"k":[0,0],"ix":1},"s":{"a":0,"k":[100,100],"ix":3},"r":{"a":0,"k":0,"ix":6},"o":{"a":0,"k":100,"ix":7},"sk":{"a":0,"k":0,"ix":4},"sa":{"a":0,"k":0,"ix":5},"nm":"Transform"}],"nm":"Group 9","np":2,"cix":2,"bm":0,"ix":9,"mn":"ADBE Vector Group","hd":false},{"ty":"gr","it":[{"ind":0,"ty":"sh","ix":1,"ks":{"a":0,"k":{"i":[[0,0.4],[1.9,2.1],[2.3,-0.3],[0.6,-0.1],[0.1,0.1],[-0.2,0.1],[-2.4,-2.4],[0.4,-3.1],[0.1,-0.9],[0.5,0.4],[0.1,1]],"o":[[0.3,-2.4],[-1.5,-1.6],[-0.6,0.1],[-0.2,0],[-0.1,-0.2],[2.9,-2.1],[2.1,2.1],[-0.1,0.9],[-0.3,1.9],[-0.9,-0.9],[0.1,-0.2]],"v":[[3.75,4],[1.85,-2.9],[-3.75,-5.1],[-5.55,-4.8],[-6.25,-5.1],[-6.05,-5.9],[2.95,-5.5],[5.95,2.1],[5.65,4.8],[4.05,7.6],[3.65,4.7]],"c":true},"ix":2},"nm":"Path 1","mn":"ADBE Vector Shape - Group","hd":false},{"ty":"fl","c":{"a":0,"k":[0.082352941176,0.082352941176,0.082352941176,1],"ix":4},"o":{"a":0,"k":100,"ix":5},"r":1,"bm":0,"nm":"Fill 1","mn":"ADBE Vector Graphic - Fill","hd":false},{"ty":"tr","p":{"a":0,"k":[103.7,513.6],"ix":2},"a":{"a":0,"k":[0,0],"ix":1},"s":{"a":0,"k":[100,100],"ix":3},"r":{"a":0,"k":0,"ix":6},"o":{"a":0,"k":100,"ix":7},"sk":{"a":0,"k":0,"ix":4},"sa":{"a":0,"k":0,"ix":5},"nm":"Transform"}],"nm":"Group 10","np":2,"cix":2,"bm":0,"ix":10,"mn":"ADBE Vector Group","hd":false},{"ty":"gr","it":[{"ind":0,"ty":"sh","ix":1,"ks":{"a":0,"k":{"i":[[1.8,-0.5],[1.3,2.4],[0.2,1.7],[2.9,2.4],[0.6,1.5],[-0.2,0.4],[-0.2,-0.2],[-1.9,-1.8],[-0.3,-2.4],[-0.4,-1.3],[-4,0.7],[-1.2,0.1],[0,-0.2],[0.2,-0.2]],"o":[[-3.1,0],[-0.8,-1.5],[-0.4,-3.8],[-1.2,-0.9],[-0.1,-0.3],[0.1,-0.1],[2.1,1.6],[1.6,1.5],[0.2,1.3],[0.9,3.9],[1.2,-0.2],[0.2,0],[0.1,0.2],[-1.7,1.8]],"v":[[4.95,11.05],[-1.55,7.45],[-2.95,2.75],[-8.05,-6.35],[-11.05,-9.65],[-10.75,-10.85],[-9.95,-10.85],[-3.75,-5.85],[-0.75,0.05],[0.15,3.95],[6.95,8.35],[10.45,7.85],[11.05,8.35],[10.85,9.15]],"c":true},"ix":2},"nm":"Path 1","mn":"ADBE Vector Shape - Group","hd":false},{"ty":"fl","c":{"a":0,"k":[0.082352941176,0.082352941176,0.082352941176,1],"ix":4},"o":{"a":0,"k":100,"ix":5},"r":1,"bm":0,"nm":"Fill 1","mn":"ADBE Vector Graphic - Fill","hd":false},{"ty":"tr","p":{"a":0,"k":[58.5,540.95],"ix":2},"a":{"a":0,"k":[0,0],"ix":1},"s":{"a":0,"k":[100,100],"ix":3},"r":{"a":0,"k":0,"ix":6},"o":{"a":0,"k":100,"ix":7},"sk":{"a":0,"k":0,"ix":4},"sa":{"a":0,"k":0,"ix":5},"nm":"Transform"}],"nm":"Group 11","np":2,"cix":2,"bm":0,"ix":11,"mn":"ADBE Vector Group","hd":false},{"ty":"gr","it":[{"ind":0,"ty":"sh","ix":1,"ks":{"a":0,"k":{"i":[[0,0],[-3.2,-4.4],[-1.1,2.5],[-0.4,-9.2],[0.5,-6.1],[0,0],[0,0],[0,0],[-9.3,7.1],[0,0],[0,0],[2.5,-13.9],[6.9,-7],[0,0],[-4.4,-6.5],[4.4,-0.3],[0.7,5.4],[0,0],[0.7,1.8],[0.7,5.9],[0,0],[-0.5,0.6],[0,0],[-0.7,0.5],[-1.8,-2.8]],"o":[[7.2,-2.2],[-4.1,-25],[5.6,-0.3],[-2.2,10.4],[0,0],[0,0],[0,0],[5.4,-31.9],[0,0],[0,0],[1,5.7],[-2.5,13.9],[0,0],[6.3,-0.2],[-4.2,0.4],[-11,-2.3],[0,0],[-12.1,-1],[-9.8,-7.8],[0,0],[-1,0.4],[0,0],[0.4,-0.1],[2.9,-1.9],[0,0]],"v":[[-33.3,-12.6],[-14.9,-2.3],[-6.9,-47.4],[1.4,-20.3],[-2.9,11],[-3.2,14.5],[-2.7,18.9],[0.3,14.7],[34.9,-46.7],[44.6,-59.1],[44.9,-40.6],[44.8,-6.3],[20.8,32.2],[12.4,38.6],[33.5,57.9],[15.1,59.1],[-0.8,40.2],[-5,38.1],[-30,23.8],[-44.4,-3.7],[-46.3,-21.3],[-46.4,-22.3],[-46.3,-21.3],[-44.7,-22.2],[-35.6,-16.2]],"c":true},"ix":2},"nm":"Path 1","mn":"ADBE Vector Shape - Group","hd":false},{"ty":"st","c":{"a":0,"k":[0,0,0,1],"ix":3},"o":{"a":0,"k":100,"ix":4},"w":{"a":0,"k":1,"ix":5},"lc":1,"lj":1,"ml":4,"bm":0,"nm":"Stroke 1","mn":"ADBE Vector Graphic - Stroke","hd":false},{"ty":"fl","c":{"a":0,"k":[1,1,1,1],"ix":4},"o":{"a":0,"k":100,"ix":5},"r":1,"bm":0,"nm":"Fill 1","mn":"ADBE Vector Graphic - Fill","hd":false},{"ty":"tr","p":{"a":0,"k":[49.95,477.3],"ix":2},"a":{"a":0,"k":[0,0],"ix":1},"s":{"a":0,"k":[100,100],"ix":3},"r":{"a":0,"k":0,"ix":6},"o":{"a":0,"k":100,"ix":7},"sk":{"a":0,"k":0,"ix":4},"sa":{"a":0,"k":0,"ix":5},"nm":"Transform"}],"nm":"Group 12","np":3,"cix":2,"bm":0,"ix":12,"mn":"ADBE Vector Group","hd":false},{"ty":"gr","it":[{"ind":0,"ty":"sh","ix":1,"ks":{"a":0,"k":{"i":[[3.2,3],[-3.5,7.4],[-3.3,-2],[-0.7,1.1],[0,0],[-3.8,-3.6],[0,0],[0,0],[6.2,3.7],[-6.9,12.6],[0,0],[-1.8,-11.6],[-2.5,-6.4],[-1.3,-5.4],[0.9,0],[1.9,-2.2],[0,0],[1.4,0.1],[3.6,-0.6],[5.1,1.2],[2.2,2.9],[2.8,3.5],[0,0]],"o":[[-3.3,-3.1],[18.3,17.8],[2.7,1.6],[0,0],[-1.7,4.1],[0,0],[0,0],[-0.9,-6.4],[9.3,-1.4],[0,0],[19.4,-6.8],[-0.2,-2],[3.2,8.2],[1.3,5.4],[-0.7,-0.1],[0,0],[-3.8,-0.3],[-1.7,-0.1],[-3.6,0.6],[-2,-0.5],[-11.6,-1.2],[0,0],[-3,-2.3]],"v":[[-61.9,1.45],[-57.1,-26.45],[-28.8,-2.05],[-23.4,-3.35],[-19.6,-0.05],[-10.6,14.85],[4.7,19.15],[11.4,14.25],[-9.3,-3.95],[22.9,-43.55],[24.6,-43.45],[55.9,-16.85],[61.3,-5.75],[63.9,14.25],[49.6,34.95],[43.1,43.35],[28.2,47.55],[17.6,48.65],[5.4,49.65],[-9.1,48.55],[-22.4,38.25],[-49.1,29.55],[-52.9,13.55]],"c":true},"ix":2},"nm":"Path 1","mn":"ADBE Vector Shape - Group","hd":false},{"ty":"fl","c":{"a":0,"k":[1,1,1,1],"ix":4},"o":{"a":0,"k":100,"ix":5},"r":1,"bm":0,"nm":"Fill 1","mn":"ADBE Vector Graphic - Fill","hd":false},{"ty":"tr","p":{"a":0,"k":[70.55,518.25],"ix":2},"a":{"a":0,"k":[0,0],"ix":1},"s":{"a":0,"k":[100,100],"ix":3},"r":{"a":0,"k":0,"ix":6},"o":{"a":0,"k":100,"ix":7},"sk":{"a":0,"k":0,"ix":4},"sa":{"a":0,"k":0,"ix":5},"nm":"Transform"}],"nm":"Group 13","np":2,"cix":2,"bm":0,"ix":13,"mn":"ADBE Vector Group","hd":false},{"ty":"gr","it":[{"ind":0,"ty":"sh","ix":1,"ks":{"a":0,"k":{"i":[[0,0],[-21.3,1.6],[-2.4,7.7]],"o":[[3.5,-6.3],[26.7,-2],[0,0]],"v":[[-73.35,33.6],[-36.15,12.7],[73.35,-33.6]],"c":false},"ix":2},"nm":"Path 1","mn":"ADBE Vector Shape - Group","hd":false},{"ty":"st","c":{"a":0,"k":[0,0,0,1],"ix":3},"o":{"a":0,"k":100,"ix":4},"w":{"a":0,"k":2,"ix":5},"lc":1,"lj":1,"ml":4,"bm":0,"nm":"Stroke 1","mn":"ADBE Vector Graphic - Stroke","hd":false},{"ty":"tr","p":{"a":0,"k":[414,35.6],"ix":2},"a":{"a":0,"k":[0,0],"ix":1},"s":{"a":0,"k":[100,100],"ix":3},"r":{"a":0,"k":0,"ix":6},"o":{"a":0,"k":100,"ix":7},"sk":{"a":0,"k":0,"ix":4},"sa":{"a":0,"k":0,"ix":5},"nm":"Transform"}],"nm":"Group 14","np":2,"cix":2,"bm":0,"ix":14,"mn":"ADBE Vector Group","hd":false},{"ty":"gr","it":[{"ind":0,"ty":"sh","ix":1,"ks":{"a":0,"k":{"i":[[-1.6,3],[0,0.1],[-1.3,2.3],[0.9,2.9],[1,1.9],[3.8,3.1],[6.8,-1.7],[0.8,0],[1.6,-0.8],[-0.5,-1.3],[-1,-3.3],[-0.7,-5.5],[-1.4,-1.1],[-2.7,-3.8],[-1.1,-1.2],[-1,0.9],[-0.4,0.6]],"o":[[0,0],[1.3,-2.3],[1.4,-2.4],[-0.6,-2.1],[-2.4,-4.2],[-5,-4],[-0.7,0.2],[-1.9,0],[-1.3,0.6],[1.2,3.2],[1.7,5.3],[0.2,1.8],[3.8,2.7],[0.9,1.3],[1,1.2],[0.6,-0.5],[1.8,-2.9]],"v":[[-20.7,52.7],[-20.8,52.6],[-17,45.6],[-15.8,38],[-17.6,31.8],[-26.4,20.4],[-43.5,15],[-45.8,15.2],[-50.9,16.7],[-51.8,19.1],[-48.1,28.7],[-44.7,45.1],[-42.4,49.2],[-32.9,59.1],[-29.8,62.9],[-27.3,63.2],[-25.7,61.6]],"c":true},"ix":2},"nm":"Path 1","mn":"ADBE Vector Shape - Group","hd":false},{"ind":1,"ty":"sh","ix":2,"ks":{"a":0,"k":{"i":[[-1.1,-1.8],[-0.2,-0.4],[0,0.1],[0.4,0.1],[0.3,2.8],[0.1,0],[0,-0.1],[0,-0.7]],"o":[[-0.3,0.2],[0,0],[0.2,-0.3],[1.3,-2.6],[0,-0.1],[-0.1,0],[-0.1,0.7],[0,1.9]],"v":[[-76.5,20.8],[-76.7,21.7],[-76.3,21.6],[-76.6,20.9],[-76.1,12.8],[-76.4,12.6],[-76.7,12.8],[-77,15]],"c":true},"ix":2},"nm":"Path 2","mn":"ADBE Vector Shape - Group","hd":false},{"ind":2,"ty":"sh","ix":3,"ks":{"a":0,"k":{"i":[[0.5,-0.9],[0.7,0.8],[2.5,1.4],[0.2,-1.3],[0.1,-1.4],[1,-1.1],[0.2,0],[0,0.1],[-0.3,0.8],[-0.2,3.5],[0.4,5.2],[1.2,3.9],[0,1],[0.9,1.2],[4.3,1.4],[1.6,-0.3],[0.7,0.7],[0,0],[-1,0.2],[-1.8,-0.7],[-2.2,-2.6],[-1,-0.8],[0,0.5],[-0.1,1.3],[-0.2,1],[-1.1,-1],[-1.1,1],[-1.8,-0.3],[-2,-1.6],[-2,-2.2],[-1.4,0.6],[-6.5,-1.8],[-1.2,-0.7],[-2.1,-3],[-1.2,-4.2],[-0.5,0],[-0.2,0.4],[-0.4,1],[-0.2,0.1],[0,-0.2],[0,0],[2.7,-4.3],[0.8,-2.4],[-0.3,-0.1],[-0.2,0.1],[-0.3,0.3],[-1.5,3.4],[-1.2,2.2],[-2.6,5.1],[-1.5,4.3],[-2.3,5.8],[-1.6,5],[-2.3,5.1],[-1.7,2.9],[-1.6,1.2],[-0.2,0.3],[0.1,0],[0.1,-0.3],[0.1,-0.4],[0.5,-0.2],[1.2,-1.2],[1.5,-2.5],[2.4,-6.6],[3.2,-7.9],[1.7,-4.9],[0.2,-0.3],[0.3,0],[0,0.4],[-0.5,1.1],[-0.8,3.1],[-0.9,2.2],[-2.1,6.1],[-4.2,6.9],[-5.1,3.4],[-3.4,1.4],[-1.9,0],[-1.7,0.1],[-2.1,-2.5],[-2.3,-5.7],[-0.2,-0.4],[-0.3,0.3],[-0.6,1.1],[-2.4,2.9],[-3.5,5.1],[-2.4,3.1],[-0.2,-0.4],[0.2,-0.3],[1.3,-1.4],[1.6,-2],[4.1,-5.3],[0.9,-1.4],[1,-2.6],[1.4,-2.9],[1.2,-2.7],[2.5,-5.6],[2,-1.5],[4.1,-2.6],[6.8,-4.2],[5.9,-5.3],[1.2,-1.1],[0.1,0.1],[0,0.2],[-0.8,0.8],[-2.4,2.4],[-2.8,1.8],[-5.8,3.9],[-3.6,2.4],[-2.3,1.8],[-0.9,2.1],[-4.3,7.8],[-0.9,1.6],[0.1,0.8],[2.9,4],[1.2,1.8],[1.9,0.9],[1,-1.1],[0.6,0.2],[2.6,-1.7],[3.1,-3.9],[0.9,-1.8],[1.5,-2.5],[1.7,-4.3],[1.4,-3.5],[0.8,-2.6],[2.5,-6.9],[1.7,-4.5],[1.1,-2.7],[-0.1,-0.5],[1.5,-2],[2.7,-2.6],[-0.6,-2.7],[-0.1,-0.7],[0.7,-0.3],[0.4,0.3],[0,0.1],[1,0.1],[1.2,-0.8],[1,-0.8],[4.3,-4],[0.5,-0.3],[0,0],[-0.5,0.6],[-2.9,1.7],[-1.2,1],[0.4,1.1],[2.8,2.7],[3.3,1.1],[0.6,0.4],[-0.7,0.6],[0,1],[0.5,1.8],[1.4,5.2],[1.9,-0.2],[-0.6,0.6],[0.7,0.8],[3.2,1.7],[2.8,-1.1],[0,-1.2],[-1.4,-4.6],[0.2,-1],[-0.2,-3.3],[0.1,-4],[-1.6,-1],[-2.2,-2.6]],"o":[[-1,-0.4],[-2,-2.2],[-1.1,-0.6],[-0.2,1.4],[-0.1,1.4],[-0.1,0.2],[-0.2,0],[0,-0.9],[0.8,-3.3],[0.3,-5.2],[-0.3,-4.2],[-0.2,-0.8],[0,-1.6],[-2.7,-3.5],[-1.6,-0.5],[-0.9,0.2],[0,0],[0.3,-0.9],[1.8,-0.3],[3,1.1],[0.8,1],[0.4,0.3],[0.1,-1.3],[0.1,-1],[0.4,-1.4],[1.4,1.3],[1.4,-1.2],[2.5,0.4],[2.3,1.8],[1,1.1],[6.4,-2.9],[1.3,0.3],[3,2],[2.5,3.5],[0.1,0.5],[0.5,0],[0.4,-0.9],[0.1,-0.2],[0.1,0.2],[0,0],[-2,4.5],[-1.4,2.2],[-0.1,0.3],[0.2,0],[0.3,-0.2],[2.2,-3],[1,-2.3],[2.7,-5.1],[2.1,-4.1],[2,-5.9],[1.9,-4.8],[1.7,-5.4],[1.4,-3],[1,-1.6],[0.2,-0.3],[0.1,-0.1],[-0.2,-0.2],[-0.1,0.4],[-0.5,-0.4],[-1.7,0.7],[-2.1,2.1],[-3.8,5.9],[-3,8],[-2,4.8],[-0.1,0.4],[-0.2,0.3],[-0.5,0],[0.3,-1.2],[1.2,-3],[0.6,-2.3],[2.3,-6.1],[2.7,-7.6],[3.3,-5.3],[3,-2],[1.7,-0.7],[1.8,0],[3.3,-0.1],[3.9,4.7],[0.2,0.5],[0.2,0.5],[0.8,-1],[1.9,-3.3],[3.9,-4.9],[2.3,-3.2],[0.3,-0.4],[0.2,0.3],[-1.1,1.5],[-1.6,1.9],[-4.1,5.4],[-1,1.3],[-1.5,2.3],[-1.2,3],[-1.3,2.8],[-2.5,5.6],[-0.2,2.7],[-3.9,2.9],[-6.7,4.3],[-6.8,4.2],[-1.2,1.1],[-0.1,0.1],[-0.1,-0.1],[0.4,-1.1],[2.5,-2.3],[2.4,-2.3],[5.8,-3.9],[3.6,-2.4],[2.4,-1.6],[1.8,-1.3],[3.5,-8.2],[0.8,-1.6],[0.4,-0.7],[-0.2,-4.8],[-1.3,-1.7],[-1.1,-1.7],[-1.1,-0.6],[-0.5,0.6],[-3.2,-1],[-4.2,2.7],[-1.3,1.6],[-1.3,2.6],[-2.3,4],[-1.4,3.5],[-1,2.5],[-2.3,7],[-1.7,4.5],[-1.1,2.7],[-0.2,0.5],[0.4,2.9],[-2.2,2.9],[-2.1,2.1],[0.1,0.7],[0.1,0.6],[-0.5,0.2],[-0.1,-0.1],[-0.5,-0.7],[-1.4,-0.1],[-1.1,0.7],[-4.6,3.6],[-0.4,0.4],[0,0],[0.1,-0.8],[2.3,-2.4],[1.3,-0.8],[1,-0.8],[-1.5,-3.6],[-2.4,-2.2],[-0.7,-0.2],[-0.8,-0.6],[0.8,-0.6],[-0.1,-1.9],[-1.3,-5.3],[-0.4,-1.4],[-0.8,0.1],[0.8,-0.9],[-2.2,-2.9],[-2.8,-1.4],[-1,0.4],[-0.1,4.7],[0.3,1],[-0.6,3.3],[0.3,3.9],[-0.1,1.8],[3,1.8],[0.7,0.7]],"v":[[-62.1,62.8],[-64.5,60.9],[-71.5,55.7],[-73.3,56.6],[-73.7,60.8],[-74.9,64.7],[-75.6,64.9],[-76.1,64.5],[-75.9,61.9],[-74.8,51.7],[-75.1,36.1],[-78.1,24.3],[-78.9,21.8],[-80.7,17.7],[-91,10.2],[-95.9,10.1],[-98.4,9.7],[-98.4,9.8],[-96.5,8.1],[-91.2,8.3],[-83.1,13.1],[-80.1,15.5],[-79,15],[-78.9,11.2],[-78.5,8.2],[-75.5,7.1],[-71.9,7],[-67.2,6.2],[-60.7,9.1],[-54.2,15],[-51.6,15.5],[-32.2,14.7],[-28.5,16.6],[-20.7,23.8],[-14.5,35.1],[-13.5,36.1],[-12.5,35.1],[-11.2,32.3],[-10.6,32],[-10.4,32.7],[-10.4,33.1],[-15.9,46.9],[-19.1,53.8],[-18.9,54.4],[-18.2,54.3],[-17.3,53.5],[-11.1,44.4],[-7.7,37.6],[-1,21.8],[3.8,9],[9.8,-8.7],[15.5,-23.3],[22.1,-38.7],[26.9,-47.4],[30.6,-51.8],[31.2,-52.7],[31.3,-53],[30.8,-52.8],[30.5,-51.7],[29.1,-51.8],[25,-48.5],[19.7,-41.5],[10.3,-22.8],[1.4,1.2],[-3.8,15.9],[-4.2,17],[-5,17.7],[-5.4,16.8],[-4.3,13.2],[-1.5,4.1],[0.9,-2.7],[7.8,-20.9],[18,-42.6],[30.6,-55.7],[39.8,-61.2],[45,-62.4],[50.3,-62.6],[58.3,-58.9],[67.5,-43.1],[68,-41.7],[69.3,-41.4],[71.5,-44.5],[78.1,-53.8],[89.6,-68.5],[96.8,-77.9],[98.1,-77.9],[98.2,-76.9],[94.7,-72.4],[90,-66.4],[77.5,-50.5],[74.7,-46.4],[70.2,-39.3],[65.6,-31],[61.4,-22.9],[54,-6.1],[50,-0.3],[38.2,8.1],[18.1,21.3],[-0.5,35.9],[-4,39.4],[-4.6,39.4],[-4.8,38.7],[-2.7,36],[4.9,29.1],[12.7,23],[30.2,11.4],[41.1,4.4],[48.1,-0.9],[51.9,-6.1],[63.2,-30.3],[65.6,-35.1],[66,-37.3],[61.9,-50.6],[58.4,-56.1],[54.1,-60.3],[51,-60.2],[49.3,-60],[40.6,-58.2],[29.6,-48.3],[26.4,-43.1],[22.4,-35.3],[16.9,-22.7],[12.6,-12.1],[9.7,-4.6],[2.3,16.2],[-3.3,29.5],[-6.6,37.6],[-7,39.1],[-9.9,45.9],[-16.8,54.5],[-18.5,61.9],[-17.9,64.1],[-18.8,65.6],[-20.2,65.3],[-20.4,65],[-22.1,63.1],[-26.1,64],[-29.1,66.3],[-42.9,77.2],[-44.5,78.2],[-44.5,78.3],[-43.4,76.3],[-36.1,69.7],[-32.5,66.8],[-31.9,64.1],[-38.5,54.8],[-46.4,49],[-48.2,47.7],[-48.4,45.9],[-47.4,43.5],[-48,37.8],[-52.3,22],[-55.1,19.6],[-55.8,17.9],[-55.8,15.6],[-64.1,9],[-72.6,8.9],[-74.3,11.2],[-74,25.2],[-73.8,28.2],[-73.7,38.1],[-73,49.9],[-70.8,54],[-63,60.6]],"c":true},"ix":2},"nm":"Path 3","mn":"ADBE Vector Shape - Group","hd":false},{"ty":"mm","mm":1,"nm":"Merge Paths 1","mn":"ADBE Vector Filter - Merge","hd":false},{"ty":"fl","c":{"a":0,"k":[0,0,0,1],"ix":4},"o":{"a":0,"k":100,"ix":5},"r":1,"bm":0,"nm":"Fill 1","mn":"ADBE Vector Graphic - Fill","hd":false},{"ty":"tr","p":{"a":0,"k":[245.95,143.1],"ix":2},"a":{"a":0,"k":[0,0],"ix":1},"s":{"a":0,"k":[100,100],"ix":3},"r":{"a":0,"k":0,"ix":6},"o":{"a":0,"k":100,"ix":7},"sk":{"a":0,"k":0,"ix":4},"sa":{"a":0,"k":0,"ix":5},"nm":"Transform"}],"nm":"Group 15","np":5,"cix":2,"bm":0,"ix":15,"mn":"ADBE Vector Group","hd":false},{"ty":"gr","it":[{"ind":0,"ty":"sh","ix":1,"ks":{"a":0,"k":{"i":[[-0.9,-0.4],[-0.2,0.6],[0.3,2.4],[-0.4,1.6],[0,1],[-0.3,3.5],[0.1,1.4],[1,0.1],[0.2,-0.8],[0.2,-1],[0.2,-3.7],[0.9,-3.2],[0,-1.4]],"o":[[0.5,0.3],[0.8,-2.2],[-0.2,-1.7],[0.2,-1],[-0.1,-3.6],[0.1,-1.4],[-0.1,-0.9],[-1.3,-0.1],[-0.2,1],[-0.8,3.6],[-0.2,3.3],[-0.4,1.3],[0.1,0.9]],"v":[[-104.4,-180.4],[-102.8,-180.9],[-101.5,-187.6],[-101.2,-192.5],[-100.7,-195.5],[-99.9,-206.1],[-99.9,-210.3],[-101.1,-212.5],[-102.2,-210.5],[-102.8,-207.5],[-104.4,-196.6],[-105.6,-186.8],[-105.8,-182.6]],"c":true},"ix":2},"nm":"Path 1","mn":"ADBE Vector Shape - Group","hd":false},{"ind":1,"ty":"sh","ix":2,"ks":{"a":0,"k":{"i":[[-0.4,-0.3],[-1.7,-0.5],[-1.8,0.4],[-2.4,0.4],[-3.9,3],[-6,4.1],[-5.5,4.7],[-1.5,1.1],[-1.9,1.4],[0,0.3],[0.2,0],[0.4,-0.1],[2.8,-1],[9.8,-4.4],[8,-4.4],[4,-2],[0.3,-0.4],[-0.4,-0.3]],"o":[[1.4,0.5],[1.8,0.6],[2.4,-0.5],[4.9,-0.8],[5.8,-4.4],[6,-4.1],[1.3,-1.2],[1.9,-1.4],[0.2,-0.1],[0,-0.1],[-0.4,0.1],[-2.8,1.1],[-10.2,3.6],[-8.4,3.7],[-3.9,2.2],[-0.4,0.2],[-0.2,0.3],[0,0.2]],"v":[[-27.4,-17.6],[-22.6,-16],[-17,-15.2],[-9.9,-16],[3.2,-21.9],[20.9,-34.6],[38.4,-47.5],[42.7,-50.7],[48.5,-55],[48.7,-55.7],[48.2,-56],[47.1,-55.7],[38.6,-52.4],[8.9,-39.5],[-15.3,-26.6],[-27,-20.1],[-28.2,-19.2],[-28.1,-18.2]],"c":true},"ix":2},"nm":"Path 2","mn":"ADBE Vector Shape - Group","hd":false},{"ind":2,"ty":"sh","ix":3,"ks":{"a":0,"k":{"i":[[0.2,0.1],[1.1,0],[2.3,-1.7],[4.2,-2.8],[4.9,-4.5],[0.2,-1.3],[-1,-1.9],[-5.3,-2.2],[-1.7,-0.9],[-1.1,0.7],[-1.7,1.5],[-5.1,4.9],[-2.1,2.6],[-0.1,0.5],[1.3,1.9],[2.7,2.8]],"o":[[-1.2,-0.8],[-2.8,0.2],[-4.2,2.9],[-5.5,3.7],[-0.9,0.9],[-0.4,2.1],[2.5,5.4],[1.7,0.7],[1.1,0.6],[1.9,-1.3],[5.4,-4.6],[2.5,-2.4],[0.3,-0.4],[0.6,-2.3],[-2.2,-3.2],[-0.5,-0.4]],"v":[[-32.2,-119.4],[-35.4,-120.5],[-43.4,-118.4],[-56.5,-110.7],[-71.7,-98],[-73.3,-94.7],[-72.4,-88.8],[-60.1,-78],[-54.8,-76.1],[-51.5,-76.3],[-45.9,-80.2],[-29.8,-94.1],[-23.1,-101.8],[-22.5,-103.2],[-23.6,-109.7],[-30.9,-118.5]],"c":true},"ix":2},"nm":"Path 3","mn":"ADBE Vector Shape - Group","hd":false},{"ind":3,"ty":"sh","ix":4,"ks":{"a":0,"k":{"i":[[0,0],[0.1,-0.8],[0.7,-2.9],[2,-5.9],[3.3,-6.2],[2.2,-3.2],[3.5,-4.2],[7.2,-6.4],[5.6,-3],[5.5,-1.3],[5.8,-0.3],[5.2,-0.1],[4.6,4],[1.1,0.7],[3.7,4.5],[0.9,4.5],[0.5,3.9],[-0.5,3.3],[-1.1,4.8],[-1.2,3.5],[-2.2,4.6],[-4.6,7],[-5.8,7],[-2.1,2.4],[-3.8,3.6],[-4.2,4.3],[-5.5,4.1],[-1.5,1.3],[-2.2,0.1],[-0.8,0.4],[-6.8,7],[-2.9,3.7],[-1.2,1.8],[-2.7,4.4],[-2.9,6.6],[-2.1,6.3],[-0.5,1.4],[0.3,0.1],[0.1,-0.1],[0.3,-0.4],[2.4,-4],[1.2,-4.4],[0.3,-0.3],[1.4,-2.3],[7.3,-7.7],[9.7,-9],[6.3,-5.7],[4,-3.9],[5.6,-6.2],[4.5,-7],[2.1,-3.1],[0.9,-1.2],[1.9,-3.3],[3.5,-9.7],[1.2,-4.1],[-0.1,-2.5],[0.1,-2.4],[-1.9,-4.3],[-0.1,-1.1],[-1.1,-2.3],[-1.2,-2.5],[-1.4,-1.9],[-5.1,-2.6],[-2.3,-0.6],[-2,-0.5],[-2.7,-0.6],[-7.6,2.8],[-1.1,0.3],[-8.2,6.8],[-4.8,3.3],[-1,0.9],[-6.1,6],[-0.9,1.3],[-2.6,4.1],[-3.2,8.8],[-1.2,6.4],[-0.4,6.6],[-0.3,5.3],[-1.3,7.7],[0,1.3],[-0.2,3.8],[-0.5,5.5],[-1.6,9.8],[0.1,0.8],[0.1,0.2],[0.1,-0.2],[0.3,-1.5],[1,-3.2],[-0.1,-0.8],[0.6,-1.8],[0.1,-1.2],[0,-5.9],[0.3,-3.9],[-0.1,-5.5],[0.3,-1],[0,0],[-0.2,2.3],[-0.2,3],[-0.1,4.4],[-0.6,6.2],[-0.7,3.2],[-0.4,2.9],[-1,3],[-1.4,3.8],[-2.6,5.3],[-4.1,9.3],[-2.3,5.4],[0.9,0.7],[0.7,-0.5],[1.2,-1],[3.2,-2.7],[1.1,0.3],[0.9,0.8],[2.2,0.8],[0.8,-1.5],[1.3,-3.2],[2.6,-6.1],[3,-4.8],[1.3,-2.3],[4.5,-5.8],[1.2,-1.8],[2.5,-2.5],[3.8,-3.1],[6.6,-2.5],[1.2,-0.8],[3,-2.6],[3.9,-3.8],[1.9,-2.1],[3,-3.4],[4.1,-4.7],[2.2,-2.8],[5.1,-8],[2,-5.7],[1,-3.5],[1.1,-4.5],[0.1,-4.5],[-1.4,-6.4],[-1.9,-2.2],[-3.9,-2.7],[-3.2,-2.1],[-3.5,-0.2],[-6.1,0.3],[-4.6,1.8],[-0.9,0.1],[-3.1,1.3],[-6,4.7],[-5.5,6.4],[-4.4,5.4],[-0.3,0.5],[-2.9,8.4],[-0.9,6.8],[-0.4,1.3],[-0.1,1],[-0.7,2.4]],"o":[[0.6,0.6],[-0.4,3],[-1.3,6.1],[-2.3,6.6],[-1.9,3.5],[-3.1,4.5],[-6.3,7.3],[-4.8,4.2],[-4.9,2.7],[-5.6,1.3],[-5.2,0.3],[-5.9,0.1],[-1,-0.8],[-4.8,-3.2],[-2.9,-3.5],[-0.7,-3.9],[-0.4,-3.3],[0.8,-4.9],[0.8,-3.6],[1.5,-4.9],[3.7,-7.6],[5,-7.7],[2,-2.4],[3.5,-3.9],[4.3,-4.1],[4.8,-4.9],[1.6,-1.2],[1.6,-1.3],[0.8,0],[8.5,-4.8],[3.3,-3.4],[1.3,-1.7],[2.8,-4.2],[3.7,-6.1],[2.6,-6.1],[0.5,-1.4],[0.1,-0.3],[-0.1,0],[-0.3,0.4],[-2.3,4.1],[-2.3,3.8],[-0.1,0.3],[-2,1.8],[-5.6,9],[-9.1,9.7],[-6.2,5.8],[-4.2,3.7],[-6,5.9],[-5.6,6.1],[-2,3.1],[-0.9,1.3],[-2.5,3.1],[-5.3,8.9],[-1.5,4.1],[-0.7,2.4],[0.1,2.4],[-0.2,4.6],[0.5,1],[0.3,2.6],[1.2,2.5],[1.1,2.2],[3.4,4.5],[2,1],[2.1,0.5],[2.7,0.8],[7.9,1.6],[1.1,-0.4],[10.2,-3.2],[4.5,-3.7],[1,-0.7],[6.4,-5.7],[1.2,-1.2],[2.8,-4],[4.9,-7.9],[2.2,-6.1],[1.2,-6.5],[0.3,-5.3],[0.4,-7.7],[0.2,-1.2],[0.1,-3.8],[0.2,-5.5],[1,-9.9],[0.1,-0.7],[0,-0.2],[-0.2,0.2],[-0.4,1.5],[-0.7,3.2],[-0.2,0.7],[0.2,1.9],[-0.4,1.2],[-0.5,5.8],[0,3.9],[-0.5,5.5],[0,1.1],[0,0],[-0.5,-2.2],[0.3,-3],[0.3,-4.4],[0.1,-6.2],[0.3,-3.3],[0.6,-2.9],[0.5,-3.2],[1.3,-3.9],[2,-5.5],[4.5,-9.1],[2.3,-5.4],[0.4,-0.8],[-0.6,-0.5],[-1.3,0.8],[-3.3,2.6],[-1,0.9],[-1.1,-0.3],[-1.8,-1.6],[-1.6,-0.6],[-1.6,3.2],[-2.5,6.1],[-2.3,5.1],[-1.4,2.3],[-3.7,6.4],[-1.3,1.7],[-2,3],[-3.5,3.6],[-5.5,4.4],[-1.3,0.5],[-3.4,2.2],[-4.1,3.6],[-2,2],[-3.2,3.3],[-4.2,4.6],[-2.3,2.7],[-6,7.4],[-3.2,5],[-1.1,3.4],[-1.2,4.4],[-1,4.3],[-0.1,6.7],[0.6,2.9],[3.1,3.6],[3.1,2.2],[2.8,1.8],[6.1,0.3],[4.8,-0.2],[0.8,-0.3],[3.4,-0.6],[7.1,-3],[6.6,-5.2],[4.6,-5.3],[0.3,-0.4],[4,-7.9],[2.2,-6.3],[0.2,-1.4],[0.3,-1],[0.3,-2.4],[0,0]],"v":[[-79.5,98],[-79.2,100.2],[-81.2,109.1],[-86.4,127],[-95.1,146.1],[-100.9,156.4],[-110.9,169.4],[-131,190.2],[-146.4,201.4],[-162,207.5],[-178.8,210.8],[-194.4,211.8],[-210.3,206.5],[-213.3,204.1],[-226,192.6],[-231.9,180.8],[-233.9,169.1],[-234.1,159.2],[-231.1,144.6],[-228.1,134],[-222.5,119.8],[-209.4,98.3],[-192.6,76.6],[-186.4,69.3],[-175.9,57.7],[-163.3,44.9],[-148.1,31],[-143.3,27.3],[-138,24.6],[-135.6,23.5],[-112.6,6],[-103.4,-4.7],[-99.4,-9.8],[-91.2,-22.7],[-80.8,-41.4],[-73.6,-59.9],[-72.1,-64.2],[-72.5,-64.8],[-72.8,-64.7],[-73.7,-63.5],[-81,-51.4],[-87.6,-39.9],[-88.3,-39],[-93.1,-32.6],[-112.9,-7.9],[-141.6,19.5],[-160.8,36.4],[-173,47.9],[-190.8,65.7],[-206.3,85],[-212.6,94.1],[-215,98],[-221.5,107.8],[-234.6,135.7],[-238.2,148.1],[-239.2,155.6],[-239.4,162.8],[-237.7,176.3],[-236.9,179.6],[-234.6,186.8],[-231,194.4],[-227.6,200.8],[-214.8,211.5],[-208.5,214.3],[-202.3,216],[-194.2,218.3],[-170.9,217],[-167.6,216],[-139.9,201.1],[-125.9,190.6],[-122.9,188.2],[-104.8,170.1],[-101.7,166.3],[-93.5,154.3],[-80.6,129.7],[-74.7,111.2],[-72.3,91.5],[-72,75.5],[-70.5,52.3],[-70.2,48.5],[-69.9,37.1],[-69.2,20.7],[-65.4,-8.8],[-65.4,-11.1],[-65.8,-11.7],[-66.3,-11.2],[-67.5,-6.8],[-69.6,2.9],[-69.8,5.2],[-70.6,10.8],[-71.4,14.5],[-72.5,32],[-73.1,43.8],[-74.2,60.2],[-74.9,63.2],[-74.8,63.2],[-75.5,56.4],[-74.7,47.3],[-73.9,34],[-73.1,15.3],[-71.8,5.5],[-70,-3.1],[-67.7,-12.3],[-63.3,-23.7],[-56,-39.7],[-42.3,-67],[-35.2,-83.1],[-34.6,-85.7],[-36.8,-84.6],[-40.5,-81.9],[-50.3,-74],[-53.4,-73.2],[-56.6,-74.4],[-62.8,-77.3],[-65.5,-76.2],[-69.1,-66.2],[-76.1,-47.6],[-83.3,-32.5],[-87.5,-25.7],[-99.4,-7.1],[-103.5,-2.1],[-110.4,6],[-121.4,16],[-139.2,26.9],[-142.9,28.9],[-152.4,36.5],[-164.2,47.8],[-170,53.9],[-179.6,63.7],[-191.8,77.9],[-198.7,86],[-214.8,109.6],[-223,125.5],[-226.6,135.6],[-230.1,148.9],[-232.1,162.1],[-229.4,181.7],[-225.7,189.6],[-215.7,199.5],[-206.4,206.1],[-197.1,209.3],[-178.8,208.9],[-164.6,206],[-162,205.3],[-152.3,202],[-132.9,189.9],[-115.1,172.1],[-101.8,155.9],[-100.9,154.6],[-88.9,130.8],[-82.5,111.7],[-81.3,107.7],[-80.6,104.7],[-78.9,97.6]],"c":true},"ix":2},"nm":"Path 4","mn":"ADBE Vector Shape - Group","hd":false},{"ind":4,"ty":"sh","ix":5,"ks":{"a":0,"k":{"i":[[0,0],[0.1,-7.4],[-0.2,-1.3],[0.2,-1.4],[2.1,0.5],[0,-1.3],[0.1,-3.2],[-0.3,-0.6],[-0.9,-0.9],[-2,-2.5],[-0.2,-0.7],[-0.4,-4.1],[0.1,-3.2],[-0.1,-0.5],[0.8,-3.6],[-1.9,-0.1],[-3.6,-2.4],[-1.2,-1.1],[-0.5,1.2],[-2,1.5],[-0.4,0.8],[-1.4,-0.1],[0,0],[1.5,-1.9],[1.1,-2.3],[0.3,-1.1],[-0.1,-0.1],[-0.2,0.2],[-4.6,3.7],[-7.2,2.5],[-1.9,0.2],[-1,-0.6],[-0.9,-1.4],[-1.5,-2],[1.2,-3.6],[0.7,-1.2],[0.1,-0.2],[-0.2,0],[-1.4,0.5],[-3.1,2],[-3.3,2.1],[-2.2,2.2],[-2.3,0.9],[-7,3],[-2.8,1.4],[-0.9,0.4],[-5.7,4.8],[-6.7,4.4],[-2.8,0.9],[-2.2,1.8],[-3.4,3.6],[-0.6,0.5],[-0.6,-0.5],[0.2,-0.6],[0.3,-0.4],[4.8,-2.9],[-0.2,-0.4],[-0.3,0],[-3.6,0.9],[-1.3,-0.2],[0,-0.7],[0.5,0],[6.8,-2.1],[2,-1.6],[2.2,-1.6],[2.2,-1.2],[1.7,-0.9],[3.8,-2.9],[5.3,-2.9],[7.2,-2.6],[3.9,-2.8],[5.9,-3.8],[0.4,-0.4],[-0.1,-0.2],[-0.1,0],[-0.3,0.1],[-1.8,0.5],[-0.7,0],[-0.1,-0.3],[0.2,-0.1],[0.5,-0.2],[2.6,-0.6],[4.8,-3.3],[0.6,-0.9],[1.1,-2],[2.2,-3.6],[1.5,-2.9],[2.5,-6.3],[2.7,-9.2],[-1.2,-0.6],[-2.4,-0.3],[-5.6,2.3],[-9.6,5.5],[-5.2,2.5],[-6.4,2.9],[-1.9,0.7],[-5.4,2],[-4.6,1.7],[-3.6,1.1],[-0.6,0.1],[-6,4.3],[-3.5,4.7],[-0.9,2.1],[1,1.9],[1.9,3.2],[-0.1,0.9],[-0.2,0.1],[-0.2,-0.4],[-1.4,-3],[-0.5,0.8],[-1.4,2.6],[-2.5,3.4],[-1.6,2],[-5.7,6.6],[-10.3,8.7],[-7.8,5.7],[-7.5,3.7],[-6.8,3.7],[-0.6,0.2],[-0.2,-0.2],[0.3,-0.2],[1.3,-0.4],[2.4,-1.2],[4.5,-2.2],[5.8,-4],[9.8,-8.9],[5.1,-5.7],[5.7,-6.8],[2.4,-3.4],[0.7,-1],[0.4,-0.8],[2.5,-6.2],[0.4,-0.6],[0.1,-0.6],[0.7,-2.7],[1.2,-1.4],[4.1,-3],[5.3,-1.9],[0.8,-1.7],[1.2,-1],[5.7,-6.7],[0.1,-0.2],[5.6,-4.3],[1.3,-1.2],[3.7,-0.8],[3.3,0.2],[0.8,0.1],[0,0],[-1.4,0.1],[-5.1,3.6],[-5.1,5],[-0.4,0.5],[-2.9,3.2],[-4.3,3.9],[-0.3,0.4],[-0.1,0.3],[0.3,-0.1],[4.2,-1.4],[0.5,-0.6],[1.6,-1],[1.3,-1],[4,-3.1],[6.1,-3.9],[4.1,-3.5],[-0.1,-0.6],[-0.6,-0.1],[-0.6,-1.4],[0,0],[1.2,0.4],[2.3,-2.1],[2.5,-0.9],[1.9,-0.8],[1.4,0.4],[3.3,1.7],[3.3,-1.5],[3.6,-0.7],[4.3,0.9],[0.4,0.1],[0.1,-0.8],[0.7,-5.7],[0.7,-6.9],[-0.1,-1.5],[-0.1,-4.5],[0.3,-5.8],[0.4,-8],[0.4,-5.2],[3.6,-9.2],[1.9,-4.2],[4.2,-6.3],[5.2,-4.8],[3.4,-3.5],[1,-0.8],[9.3,-6.3],[3.4,-1.2],[4.7,-1.4],[7.8,1.5],[3,0.8],[4,2.1],[3.5,4.6],[1.2,2.6],[1.1,2.8],[0.6,1.9],[0.3,0.8],[-0.1,5.4],[0,2.2],[-0.8,3.1],[-2.2,5.5],[-3,5.4],[-5.3,8],[-5.4,6.3],[-5.6,5.4],[-5.2,4.8],[-4.8,4],[-6.2,5.6],[-5.4,5.9],[-3.6,4.7],[-3.7,5.3],[-0.1,0.3],[0.8,1],[1.3,1.6],[10,12.7],[0.5,0.4],[1.1,3.7],[0.8,2.6],[0,0.6],[-1.8,7],[-1.2,3.3],[0.4,1.8],[-0.3,1.7],[0.2,8],[-0.7,1.5],[-0.9,0.1],[-0.4,-0.8],[0.7,-1.8],[0.3,-0.8],[1.1,1.3],[0.3,0],[0.1,-0.1],[0,-0.5],[1.6,-8.3],[0.1,-0.5],[-0.6,-1.2],[-0.3,0.1],[-0.1,1.4],[0,2.2],[0,4.4],[-0.2,1.5],[0,-1.1],[0.1,-2.2],[-0.5,-3.6],[0.4,-1.8],[2.1,-0.5],[0.7,-0.3],[0.3,-0.8],[0.8,-4.7],[-0.1,-3.8],[0,-0.9],[-2,-3.7],[-0.2,-0.8],[-2.2,-2.7],[-2.5,-3.3],[-6.5,-7.7],[-2.6,-2.6],[-0.9,1.4],[-4.4,8.1],[-0.3,0.6],[-2,2.7],[0.7,0.7],[1.2,1.7],[0.6,2.1],[0.6,1.5],[-0.4,2],[1.9,1.5],[0.7,0.7],[5.3,0.2],[0.3,0],[0.3,1.2],[-0.4,0.6],[0,2.8],[0.7,4.3],[1.2,3.4],[1,1.6],[2.3,3.5],[4.3,1.1],[1.8,0.1],[0,0.6],[-0.6,0.1],[-0.3,-0.2],[-2.9,-2],[-0.2,0.6],[-0.1,0.2],[-0.5,5.3],[0.1,2.7],[-0.9,5.6],[-0.1,0.2],[-1.5,0.1],[-0.6,-1.2],[-0.4,-0.9]],"o":[[-1,7.3],[0,1.3],[0.2,1.5],[-0.3,2.2],[-1.4,-0.4],[-0.1,3.2],[0,0.6],[0.6,1.1],[2.3,2.5],[0.5,0.6],[1.3,3.8],[0.3,3.2],[0,0.5],[1,3.7],[-0.5,2.2],[4.5,0.3],[1.3,0.9],[1,0.9],[1,-2.3],[0.8,-0.6],[0.5,-1],[0,0],[-1.1,2.2],[-1.6,2],[-0.5,1],[0,0.2],[0.2,0.1],[4.7,-3.5],[5.9,-4.7],[1.8,-0.7],[1.2,-0.1],[1.4,0.9],[1.4,2.1],[2.1,2.9],[-0.4,1.3],[-0.1,0.2],[0.2,0],[1.4,0],[3.4,-1.4],[3.3,-2.1],[2.6,-1.7],[1.8,-1.9],[7.2,-2.5],[2.9,-1.3],[0.9,-0.5],[6.8,-3],[6.2,-5.1],[2.4,-1.6],[2.6,-0.9],[3.8,-3.2],[0.5,-0.6],[0.5,-0.4],[0.6,0.5],[-0.2,0.5],[-3.7,4],[-0.3,0.2],[0.1,0.2],[3.6,-0.8],[1.2,-0.3],[0.7,0.1],[-0.1,0.6],[-7.3,-0.5],[-2.4,0.7],[-2.2,1.7],[-2,1.5],[-1.8,1],[-4.4,2.2],[-4.9,3.7],[-6.8,3.6],[-4.6,1.6],[-5.7,4.1],[-0.4,0.3],[-0.1,0.1],[0,0.1],[0.4,0],[1.9,-0.5],[0.6,-0.2],[0.3,0],[0.1,0.1],[-0.4,0.2],[-2.6,0.7],[-5.7,1.3],[-0.9,0.6],[-1.3,1.9],[-2,3.7],[-1.7,2.7],[-3.1,6],[-3.6,8.8],[-0.4,1.3],[2.2,1],[6.1,0.7],[10.3,-4.1],[5,-2.8],[6.3,-3],[1.9,-0.8],[5.3,-2.1],[4.6,-1.7],[3.6,-1.3],[0.6,-0.2],[7.2,-1.7],[4.8,-3.5],[1.4,-1.8],[0.7,-1.7],[0,-3.7],[-0.5,-0.8],[0,-0.4],[0.7,-0.4],[1.3,3],[0.4,0.9],[1.5,-2.5],[2,-3.7],[1.5,-2],[5.4,-6.9],[8.8,-10.3],[7.4,-6.3],[6.8,-5],[7,-3.4],[0.6,-0.3],[0.3,-0.1],[0.3,0.3],[-1.2,0.8],[-2.6,0.9],[-4.4,2.3],[-6.3,3.1],[-10.8,7.6],[-5.6,5.1],[-6,6.6],[-2.7,3.2],[-0.7,1],[-0.5,0.7],[-3,5.9],[-0.3,0.7],[-0.3,0.5],[-0.4,2.8],[-0.5,1.9],[-3.4,3.8],[-4.5,3.4],[-1.6,0.6],[-0.7,1.3],[-6.7,5.8],[-0.2,0.2],[-3.9,5.9],[-1.4,1.1],[-2.9,2.5],[-3.2,0.7],[-0.9,-0.1],[0,0],[1.2,-0.8],[6.2,-0.3],[5.9,-4.1],[0.5,-0.4],[2.8,-3.3],[4,-4.3],[0.4,-0.3],[0.2,-0.3],[-0.4,-0.1],[-4.2,1.3],[-0.8,0.3],[-1.2,1.7],[-1.4,0.8],[-4.1,3],[-5.7,4.4],[-4.5,2.9],[-0.4,0.3],[0.1,0.7],[1.5,0.2],[0,0],[-1.3,0.5],[-2.9,-1.1],[-2,1.9],[-1.9,0.7],[-1.4,0.6],[-3.4,-1],[-3,-1.5],[-3.3,1.5],[-4.5,0.9],[-0.4,-0.1],[-0.7,-0.2],[-1.2,5.6],[-0.8,6.8],[-0.2,1.5],[0.2,4.6],[0.1,5.9],[-0.3,8],[-0.2,5.2],[-0.7,9.8],[-1.7,4.3],[-3.3,7],[-3.9,5.8],[-3.6,3.4],[-0.9,0.9],[-8.8,6.9],[-3,2],[-4.6,1.6],[-7.7,2.2],[-3,-0.6],[-4.3,-1.1],[-5.1,-2.7],[-1.7,-2.2],[-1.3,-2.8],[-0.7,-1.9],[-0.2,-0.9],[-2.1,-5.1],[0.1,-2.2],[0,-3.2],[1.5,-5.8],[2.3,-5.7],[4.6,-8.4],[4.6,-6.9],[5.1,-5.9],[5.2,-4.9],[4.6,-4.2],[6.5,-5.3],[6,-5.3],[4,-4.4],[4,-5.1],[0.1,-0.2],[0.7,-1.1],[-1.3,-1.6],[-10.6,-12.2],[-0.4,-0.5],[-2.8,-2.6],[-0.8,-2.6],[-0.2,-0.6],[-0.6,-7.1],[0.9,-3.5],[0.6,-1.7],[-0.4,-1.8],[1.3,-7.9],[0,-1.6],[0.4,-0.9],[0.8,0],[0.9,1.6],[-0.3,0.8],[-0.1,-1.5],[-0.1,-0.1],[-0.1,0],[-0.1,0.5],[-1.1,8.4],[-0.1,0.5],[-0.2,1.6],[0.1,0.1],[1.3,-0.7],[0.3,-2.1],[-0.1,-4.4],[0,-1.5],[0.8,1],[-0.1,2.2],[-0.2,3.7],[0.2,1.8],[-0.5,2],[-0.7,0.2],[-0.7,0.3],[-1.4,4.5],[-0.6,3.8],[0,0.9],[-0.1,4.2],[0.4,0.7],[1.1,3.3],[2.7,3.2],[6.1,8],[2.4,2.8],[1.3,1.2],[4.9,-7.8],[0.3,-0.6],[1.2,-3.1],[0.6,-0.8],[-1.6,-1.4],[-1.2,-1.8],[-0.4,-1.6],[-0.7,-1.9],[0.5,-2.3],[-0.8,-0.6],[-3.9,-3.6],[-0.3,0],[-0.8,-0.1],[-0.2,-1],[1.8,-2.2],[-0.1,-4.3],[-0.5,-3.5],[-0.6,-1.7],[-2.2,-3.5],[-2.4,-3.6],[-1.7,-0.4],[-0.5,0],[0,-0.7],[0.3,-0.1],[3.2,1.2],[0.6,0.5],[0.1,-0.2],[0.6,-5.3],[0.3,-2.7],[-0.3,-5.7],[0,-0.2],[0.5,-1],[1.4,0],[0.5,0.9],[0,0]],"v":[[-97.6,-210.8],[-100.2,-188.9],[-100,-185.1],[-100.2,-180.6],[-104.3,-178],[-105.9,-176.9],[-106.2,-167.4],[-105.6,-165.6],[-103.5,-162.4],[-98.1,-154.2],[-97.1,-152.2],[-93.8,-140.5],[-93.2,-131],[-93.2,-129.5],[-93.9,-118.6],[-92.3,-115.8],[-80.5,-110.9],[-76.9,-107.5],[-74.5,-107.9],[-70.1,-113.6],[-68.7,-115.8],[-66.2,-117.8],[-66.2,-117.9],[-70.2,-111.9],[-74.1,-105.3],[-75,-102],[-74.8,-101.4],[-74.1,-101.4],[-60,-111.8],[-40.1,-122.2],[-34.4,-122.9],[-31.2,-121.8],[-27.7,-118.3],[-23.2,-112.2],[-21.5,-102.4],[-23.6,-98.8],[-23.8,-98.1],[-23.1,-98],[-19,-99],[-9.1,-103.9],[0.8,-110.3],[8,-116],[14.5,-119.9],[35.5,-129],[44,-133.3],[46.7,-134.8],[65.1,-147],[84.4,-161.4],[92,-165.6],[98.8,-170.5],[109.1,-181.2],[110.7,-182.8],[112.4,-182.9],[112.9,-181.2],[112.1,-179.9],[100.7,-168.2],[100.2,-167.3],[101.2,-167.1],[112,-169.6],[115.8,-170],[116.9,-168.7],[115.9,-167.8],[95.2,-163.3],[88.6,-159.5],[82.1,-154.3],[75.8,-150.1],[70.6,-147],[58.8,-138.6],[43.2,-129.1],[22.1,-120.1],[9.5,-113.1],[-8.1,-101.6],[-9.3,-100.6],[-9.3,-100.2],[-9.1,-100],[-8,-100.1],[-2.5,-101.6],[-0.6,-101.9],[0.1,-101.1],[-0.2,-100.5],[-1.6,-99.9],[-9.4,-97.9],[-24.8,-90.4],[-26.8,-88.1],[-30.5,-82.3],[-37.1,-71.6],[-41.9,-63.3],[-51,-45.2],[-61.1,-18.4],[-60.2,-16.3],[-53.2,-14.7],[-35.7,-17.8],[-6.4,-33.3],[8.9,-41.2],[28,-49.9],[33.6,-52.2],[49.6,-58.4],[63.6,-63.4],[74.3,-67.3],[76.1,-67.9],[95.4,-77.6],[107.5,-90.2],[110.7,-96.2],[111.2,-101.7],[108.4,-111.9],[107.8,-114.5],[108.1,-115.5],[109.2,-114.8],[113.2,-105.7],[114.9,-105.5],[119.2,-113.2],[125.7,-124],[129.9,-130.4],[146.4,-150.9],[175.2,-179.2],[197.9,-197.2],[219.5,-210.1],[240,-221.1],[241.7,-221.9],[242.6,-221.4],[242.4,-220.5],[238.8,-218.4],[231.6,-214.9],[218.3,-208.1],[200.3,-197.3],[169.3,-172.5],[153.1,-156.4],[135.9,-136],[128.6,-125.8],[126.4,-122.7],[124.9,-120.5],[115.7,-102.9],[114.5,-101],[113.5,-99.4],[110.5,-91.6],[107.4,-86.9],[96.5,-76.3],[81.9,-68.2],[78.2,-65.2],[75.1,-61.9],[57,-42.8],[56.5,-42.2],[41.5,-27.7],[37.2,-24.5],[27.3,-19.8],[17.5,-18.7],[14.9,-19.1],[14.9,-19],[19,-19.9],[36.1,-25.6],[52.4,-39.4],[53.7,-40.8],[62.1,-50.7],[74.1,-63.4],[75.2,-64.5],[75.5,-65.5],[74.4,-65.7],[61.7,-61.6],[59.4,-60.3],[54.7,-57.1],[50.4,-54.7],[38.2,-45.6],[20.5,-33],[7.5,-23.6],[6.7,-22.4],[8.1,-21.3],[11.4,-19],[11.3,-19.1],[7.6,-19.6],[-0.2,-18.3],[-7.2,-14.6],[-13,-12.6],[-17.1,-12.4],[-27.3,-15.6],[-36.9,-15.7],[-47.2,-12.7],[-60.4,-13.6],[-61.5,-14],[-62.9,-13.2],[-65.9,3.7],[-68.2,24.2],[-68.5,28.8],[-68.8,42.5],[-69.9,60],[-70.7,84],[-71.6,99.6],[-78.3,128.1],[-84,140.6],[-95.7,160.2],[-108.9,176.5],[-119.2,187.2],[-122,189.8],[-148.9,209.9],[-158.4,214.7],[-172.1,219.5],[-195.5,220.5],[-204.3,217.9],[-216.7,213],[-229.8,202.1],[-233.6,194.6],[-237.3,186.2],[-239.1,180.4],[-239.7,177.8],[-241.7,162],[-241.6,155.5],[-240.1,146.1],[-234.5,129.1],[-226.5,112.6],[-211,88.5],[-195.9,68.8],[-179.9,51.9],[-164.5,37.1],[-150.5,24.7],[-132,7.6],[-114.7,-9.1],[-102.9,-22.6],[-91.8,-38.6],[-91.4,-39.3],[-91.6,-42.4],[-95.4,-47.2],[-126.4,-84.5],[-127.6,-86],[-133.1,-95.4],[-136,-103.2],[-136.5,-105],[-135.9,-126.2],[-132.9,-136.4],[-132.3,-141.6],[-131.9,-146.9],[-129.7,-170.8],[-128.8,-175.3],[-126.7,-176.7],[-124.8,-175.5],[-124.1,-170.4],[-125,-167.9],[-126,-172.3],[-126.7,-172.4],[-127,-172.2],[-127.3,-170.7],[-130.5,-145.4],[-130.7,-143.9],[-128.9,-140.3],[-127.9,-140.3],[-125.8,-143.7],[-125.4,-150.2],[-125.6,-163.5],[-125.1,-168],[-124.3,-164.8],[-124.5,-158.3],[-124,-147.3],[-124.1,-142],[-127.6,-138],[-129.7,-137.1],[-131.2,-135.5],[-134.8,-121.8],[-134.9,-110.4],[-134.8,-107.7],[-131.7,-96],[-130.7,-93.9],[-125.2,-85.2],[-117.5,-75.3],[-98,-52.3],[-90.6,-44.1],[-87.9,-44.2],[-73.4,-67.6],[-72.5,-69.3],[-68,-78.1],[-68.2,-80.1],[-72.1,-84.8],[-74.9,-90.6],[-76.4,-95.3],[-76.9,-101.3],[-79,-107],[-81.2,-109.1],[-95.2,-114.4],[-96,-114.3],[-98.2,-115.2],[-97.1,-117],[-94.3,-124.7],[-95.1,-137.6],[-97.4,-148],[-99.6,-152.9],[-106.3,-163.5],[-116.2,-170.8],[-121.5,-171.7],[-122.5,-172.5],[-121.4,-173.8],[-120.3,-173.7],[-110.7,-170.2],[-109.2,-170.7],[-109,-171.4],[-106.5,-187.1],[-106,-195.1],[-104.2,-211.8],[-104,-212.5],[-101.8,-214.9],[-98.7,-213.1],[-97.5,-210.3]],"c":true},"ix":2},"nm":"Path 5","mn":"ADBE Vector Shape - Group","hd":false},{"ty":"mm","mm":1,"nm":"Merge Paths 1","mn":"ADBE Vector Filter - Merge","hd":false},{"ty":"fl","c":{"a":0,"k":[0,0,0,1],"ix":4},"o":{"a":0,"k":100,"ix":5},"r":1,"bm":0,"nm":"Fill 1","mn":"ADBE Vector Graphic - Fill","hd":false},{"ty":"tr","p":{"a":0,"k":[245.05,363.6],"ix":2},"a":{"a":0,"k":[0,0],"ix":1},"s":{"a":0,"k":[100,100],"ix":3},"r":{"a":0,"k":0,"ix":6},"o":{"a":0,"k":100,"ix":7},"sk":{"a":0,"k":0,"ix":4},"sa":{"a":0,"k":0,"ix":5},"nm":"Transform"}],"nm":"Group 16","np":9,"cix":2,"bm":0,"ix":16,"mn":"ADBE Vector Group","hd":false}],"ip":0,"op":450.000018328876,"st":0,"bm":0}]}],"layers":[{"ddd":0,"ind":1,"ty":0,"nm":"색 O 일러","refId":"comp_0","sr":1,"ks":{"o":{"a":0,"k":100,"ix":11},"r":{"a":0,"k":0,"ix":10},"p":{"a":0,"k":[147.95,504.6,0],"ix":2},"a":{"a":0,"k":[68.2,77.35,0],"ix":1},"s":{"a":0,"k":[100,100,100],"ix":6}},"ao":0,"hasMask":true,"masksProperties":[{"inv":false,"mode":"n","pt":{"a":0,"k":{"i":[[0,0],[0,0],[-4,-2],[0,0],[0,0],[0,0],[-7,-4],[0,0]],"o":[[0,0],[0,0],[4,2],[0,0],[0,0],[0,0],[7,4],[0,0]],"v":[[77.25,3.75],[150.25,102.75],[5.25,24.75],[138.25,141.75],[-29.75,44.75],[98.25,164.75],[-53.75,92.75],[67.25,193.75]],"c":false},"ix":1},"o":{"a":0,"k":100,"ix":3},"x":{"a":0,"k":0,"ix":4},"nm":"Mask 1"}],"ef":[{"ty":22,"nm":"Stroke","np":13,"mn":"ADBE Stroke","ix":1,"en":1,"ef":[{"ty":10,"nm":"Path","mn":"ADBE Stroke-0001","ix":1,"v":{"a":0,"k":1,"ix":1}},{"ty":7,"nm":"All Masks","mn":"ADBE Stroke-0010","ix":2,"v":{"a":0,"k":0,"ix":2}},{"ty":7,"nm":"Stroke Sequentially","mn":"ADBE Stroke-0011","ix":3,"v":{"a":0,"k":1,"ix":3}},{"ty":2,"nm":"Color","mn":"ADBE Stroke-0002","ix":4,"v":{"a":0,"k":[1,1,1,1],"ix":4}},{"ty":0,"nm":"Brush Size","mn":"ADBE Stroke-0003","ix":5,"v":{"a":0,"k":30.1,"ix":5}},{"ty":0,"nm":"Brush Hardness","mn":"ADBE Stroke-0004","ix":6,"v":{"a":0,"k":0.75,"ix":6}},{"ty":0,"nm":"Opacity","mn":"ADBE Stroke-0005","ix":7,"v":{"a":0,"k":1,"ix":7}},{"ty":0,"nm":"Start","mn":"ADBE Stroke-0008","ix":8,"v":{"a":0,"k":0,"ix":8}},{"ty":0,"nm":"End","mn":"ADBE Stroke-0009","ix":9,"v":{"a":1,"k":[{"i":{"x":[0.833],"y":[0.833]},"o":{"x":[0.167],"y":[0.167]},"t":56,"s":[0]},{"t":96.0000039101602,"s":[100]}],"ix":9}},{"ty":7,"nm":"Spacing","mn":"ADBE Stroke-0006","ix":10,"v":{"a":0,"k":15,"ix":10}},{"ty":7,"nm":"Paint Style","mn":"ADBE Stroke-0007","ix":11,"v":{"a":0,"k":3,"ix":11}}]}],"w":137,"h":155,"ip":0,"op":450.000018328876,"st":0,"bm":0},{"ddd":0,"ind":2,"ty":0,"nm":"색 ㅌ 일러","refId":"comp_1","sr":1,"ks":{"o":{"a":0,"k":100,"ix":11},"r":{"a":0,"k":0,"ix":10},"p":{"a":0,"k":[324.825,303.925,0],"ix":2},"a":{"a":0,"k":[244.675,292.925,0],"ix":1},"s":{"a":0,"k":[100,100,100],"ix":6}},"ao":0,"hasMask":true,"masksProperties":[{"inv":false,"mode":"n","pt":{"a":0,"k":{"i":[[0,0],[0,0],[-3,0],[0,0],[0,0],[0,0],[1,-5],[0,0],[0,0],[0,0],[0,0],[0,0],[0,0],[0,0],[0,0],[0,0],[0,0],[0,0]],"o":[[0,0],[0,0],[3,0],[0,0],[0,0],[0,0],[-1,5],[0,0],[0,0],[0,0],[0,0],[0,0],[0,0],[0,0],[0,0],[0,0],[0,0],[0,0]],"v":[[451.85,4],[512.85,223],[345.85,21],[464.85,287],[261.85,49],[378.85,323],[178.85,105],[328.85,373],[105.85,134],[255.85,410],[53.85,260],[196.85,485],[49.85,390],[166.85,555],[15.85,423],[113.85,592],[-29.15,481],[44.85,610]],"c":false},"ix":1},"o":{"a":0,"k":100,"ix":3},"x":{"a":0,"k":0,"ix":4},"nm":"Mask 1"}],"ef":[{"ty":22,"nm":"Stroke","np":13,"mn":"ADBE Stroke","ix":1,"en":1,"ef":[{"ty":10,"nm":"Path","mn":"ADBE Stroke-0001","ix":1,"v":{"a":0,"k":1,"ix":1}},{"ty":7,"nm":"All Masks","mn":"ADBE Stroke-0010","ix":2,"v":{"a":0,"k":0,"ix":2}},{"ty":7,"nm":"Stroke Sequentially","mn":"ADBE Stroke-0011","ix":3,"v":{"a":0,"k":1,"ix":3}},{"ty":2,"nm":"Color","mn":"ADBE Stroke-0002","ix":4,"v":{"a":0,"k":[1,1,1,1],"ix":4}},{"ty":0,"nm":"Brush Size","mn":"ADBE Stroke-0003","ix":5,"v":{"a":0,"k":60.7,"ix":5}},{"ty":0,"nm":"Brush Hardness","mn":"ADBE Stroke-0004","ix":6,"v":{"a":0,"k":0.75,"ix":6}},{"ty":0,"nm":"Opacity","mn":"ADBE Stroke-0005","ix":7,"v":{"a":0,"k":1,"ix":7}},{"ty":0,"nm":"Start","mn":"ADBE Stroke-0008","ix":8,"v":{"a":0,"k":0,"ix":8}},{"ty":0,"nm":"End","mn":"ADBE Stroke-0009","ix":9,"v":{"a":1,"k":[{"i":{"x":[0.833],"y":[0.833]},"o":{"x":[0.167],"y":[0.167]},"t":0,"s":[0]},{"t":51.0000020772726,"s":[100]}],"ix":9}},{"ty":7,"nm":"Spacing","mn":"ADBE Stroke-0006","ix":10,"v":{"a":0,"k":15,"ix":10}},{"ty":7,"nm":"Paint Style","mn":"ADBE Stroke-0007","ix":11,"v":{"a":0,"k":3,"ix":11}}]}],"w":490,"h":586,"ip":0,"op":450.000018328876,"st":0,"bm":0}],"markers":[]}